Workbook

Sheet Apuração
B3: Apuração PIS/COFINS - SAP
B4: SOMPO SERVICES
D5: 01.2026 | E5: 02.2026 | F5: 03.2026 | G5: 04.2026 | H5: 05.2026 | I5: 06.2026 | J5: 07.2026 | K5: 08.2026 | L5: 09.2026 | M5: 10.2026 | N5: 11.2026 | O5: 12.2026 | Q5: 05.2026
C6: RECEITAS - PRESTAÇÃO DE SERVIÇO
B7: 35199998 | C7: RECEITAS PREST SERV | D7: =IFERROR(VLOOKUP(B7,'Bal 012026'!B:H,6,0),0) -> -7990.17 | E7: =IFERROR(VLOOKUP(B7,'Bal 022026'!$B:$H,6,0),0) -> -3906.58 | F7: =IFERROR(VLOOKUP($B$7,'Bal 032026'!$B:$H,6,0),0) -> -4605.8 | G7: =IFERROR(VLOOKUP(B7,'Bal 042026'!B:H,6,0),0) -> -2559.73 | H7: =IFERROR(VLOOKUP(B7,'Bal 052026'!B:H,6,0),0) -> -6624.52 | I7: =IFERROR(VLOOKUP(B7,'Bal 06.2026'!B:H,6,0),0) -> -7391.75 | J7: =IFERROR(VLOOKUP(B7,'Bal 07.2026'!A:G,6,0),0) -> 0 | K7: =IFERROR(VLOOKUP(B7,'Bal 08.2026'!A:G,6,0),0) -> 0 | L7: =VLOOKUP(B7,'Bal 09.2026'!A:G,6,0) -> #N/A | M7: =VLOOKUP(B7,'Bal 10.2026'!A:G,6,0) -> #N/A | N7: =IFERROR(VLOOKUP(B7,'Bal 11.2026'!A:G,6,0),0) -> 0 | O7: =IFERROR(VLOOKUP(B7,'Bal 12.2026'!A:G,6,0),0) -> 0 | Q7: 0
B8: 35199995 | C8: Receita SompoRisk | D8: =IFERROR(VLOOKUP(B8,'Bal 012026'!B:H,6,0),0) -> -37147.5 | E8: =IFERROR(VLOOKUP(B8,'Bal 022026'!$B:$H,6,0),0) -> -40552 | F8: =IFERROR(VLOOKUP($B$8,'Bal 032026'!$B:$H,6,0),0) -> -33550 | G8: =IFERROR(VLOOKUP(B8,'Bal 042026'!B:H,6,0),0) -> -55209.5 | H8: =IFERROR(VLOOKUP(B8,'Bal 052026'!B:H,6,0),0) -> -85622.5 | I8: =IFERROR(VLOOKUP(B8,'Bal 06.2026'!B:H,6,0),0) -> -79219 | O8: =IFERROR(VLOOKUP(B8,'Bal 12.2026'!A:G,6,0),0) -> 0 | P8: A100 | Q8: -85622.5
C9: TOTAL RECEITAS PRESTAÇÃO DE SERVIÇO | D9: =SUM(D7:D8) -> -45137.67 | E9: =SUM(E7:E8) -> -44458.58 | F9: =SUM(F7:F8) -> -38155.8 | G9: =SUM(G7:G8) -> -57769.23 | H9: =SUM(H7:H8) -> -92247.02 | I9: =SUM(I7:I8) -> -86610.75 | J9: =SUM(J7:J7) -> 0 | K9: =SUM(K7:K7) -> 0 | L9: =SUM(L7:L7) -> #N/A | M9: =SUM(M7:M7) -> #N/A | N9: =SUM(N7:N7) -> 0 | O9: =SUM(O7:O8) -> 0 | Q9: -85622.5
B10: 0.0165 | C10: PIS SOBRE RECEITA (1,65%) | D10: =D9*B10 -> -744.77156 | E10: =E9*1.65% -> -733.56657 | F10: =F9*1.65% -> -629.5707 | G10: =G9*1.65% -> -953.1923 | H10: =H9*1.65% -> -1522.0758 | I10: =I9*1.65% -> -1429.0774 | J10: =J9*1.65% -> 0 | K10: =K9*1.65% -> 0 | L10: =L9*1.65% -> #N/A | ... O10: =O9*1.65% -> 0 | Q10: -1412.7713
B11: 0.076 | C11: COFINS SOBRE RECEITA (7,60%) | D11: =D9*B11 -> -3430.4629 | E11: =E9*B11 -> -3378.8521 | F11: =F9*7.6% -> -2899.8408 | G11: =G9*7.6% -> -4390.4615 | H11: =H9*7.6% -> -7010.7735 | I11: =I9*7.6% -> -6582.417 | J11: =J9*7.6% -> 0 | K11: =K9*7.6% -> 0 | L11: =L9*7.6% -> #N/A | M11: =M9*7.6% -> #N/A | ... O11: =O9*7.6% -> 0 | Q11: -6507.31
C13: RECEITAS FINANCEIRAS
B14: 36114001 | C14: FDO ÑEX VC (DPV)GAIN | D14: =IFERROR(VLOOKUP(B14,'Bal 012026'!B:H,6,0),0) -> -6200.26 | E14: =IFERROR(VLOOKUP($B$14,'Bal 022026'!$B:$H,6,0),0) -> -6152.41 | F14: =IFERROR(VLOOKUP(B14,'Bal 032026'!$B:$H,6,0),0) -> -7276.93 | G14: =IFERROR(VLOOKUP(B14,'Bal 042026'!B:H,6,0),0) -> -6578.34 | H14: =IFERROR(VLOOKUP(B14,'Bal 052026'!B:H,6,0),0) -> -6759.61 | I14: =IFERROR(VLOOKUP(B14,'Bal 06.2026'!B:H,6,0),0) -> -6936.26 | J14: =IFERROR(VLOOKUP(B14,'Bal 07.2026'!A:G,6,0),0) -> 0 | K14: =IFERROR(VLOOKUP(B14,'Bal 08.2026'!A:G,6,0),0) -> 0 | L14: =IFERROR(VLOOKUP(B14,'Bal 09.2026'!A:G,6,0),0) -> 0 | M14: =IFERROR(VLOOKUP(B14,'Bal 10.2026'!A:G,6,0),0) -> 0 | N14: =IFERROR(VLOOKUP(B14,'Bal 11.2026'!A:G,6,0),0) -> 0 | O14: =IFERROR(VLOOKUP(B14,'Bal 12.2026'!A:G,6,0),0) -> 0 | P14: F100 | Q14: 0
B15: 36910001 | C15: JUROS S/CRED.TRIBUT | D15: =IFERROR(VLOOKUP(B15,'Bal 012026'!B:H,6,0),0) -> -8252 | E15: =IFERROR(VLOOKUP($B$15,'Bal 022026'!$B:$H,6,0),0) -> -7113.78 | F15: -8607.69 | G15: =IFERROR(VLOOKUP(B15,'Bal 042026'!B:H,6,0),0) -> -4495.54 | H15: =IFERROR(VLOOKUP(B15,'Bal 052026'!B:H,6,0),0) -> -7611.75 | I15: =IFERROR(VLOOKUP(B15,'Bal 06.2026'!B:H,6,0),0) -> -7967.44 | J15: =IFERROR(VLOOKUP(B15,'Bal 07.2026'!A:G,6,0),0) -> 0 | K15: =IFERROR(VLOOKUP(B15,'Bal 08.2026'!A:G,6,0),0) -> 0 | L15: =IFERROR(VLOOKUP(B15,'Bal 09.2026'!A:G,6,0),0) -> 0 | M15: =IFERROR(VLOOKUP(B15,'Bal 10.2026'!A:G,6,0),0) -> 0 | N15: =IFERROR(VLOOKUP(B15,'Bal 11.2026'!A:G,6,0),0) -> 0 | O15: =IFERROR(VLOOKUP(B15,'Bal 12.2026'!A:G,6,0),0) -> 0 | Q15: 0
B16: 36990099 | C16: OUTRAS REC.FINAN EV | D16: =IFERROR(VLOOKUP(B16,'Bal 012026'!B:H,6,0),0) -> -528.68 | E16: =IFERROR(VLOOKUP($B$16,'Bal 022026'!$B:$H,6,0),0)*0-'Bal 022026'!F148 -> -528.68 | F16: =IFERROR(VLOOKUP(B16,'Bal 032026'!$B:$H,6,0),0) -> -528.68 | G16: =IFERROR(VLOOKUP(B16,'Bal 042026'!B:G,6,0),0) -> -528.68 | H16: =IFERROR(VLOOKUP(B16,'Bal 052026'!B:H,6,0),0) -> -628.24 | I16: =IFERROR(VLOOKUP(B16,'Bal 06.2026'!B:H,6,0),0) -> -1337.18 | J16: =IFERROR(VLOOKUP(B16,'Bal 07.2026'!A:G,6,0),0) -> 0 | K16: =IFERROR(VLOOKUP(B16,'Bal 08.2026'!A:G,6,0),0) -> 0 | L16: =IFERROR(VLOOKUP(B16,'Bal 09.2026'!A:G,6,0),0) -> 0 | M16: =IFERROR(VLOOKUP(B16,'Bal 10.2026'!A:G,6,0),0) -> 0 | N16: =IFERROR(VLOOKUP(B16,'Bal 11.2026'!A:G,6,0),0) -> 0 | O16: =IFERROR(VLOOKUP(B16,'Bal 12.2026'!A:G,6,0),0) -> 0 | Q16: 0
C17: TOTAL RECEITAS FINANCEIRA | D17: =SUM(D14:D16) -> -14980.94 | E17: =SUM(E14:E16) -> -13794.87 | F17: =SUM(F14:F16) -> -16413.3 | G17: =SUM(G14:G16) -> -11602.56 | H17: =SUM(H14:H16) -> -14999.6 | I17: =SUM(I14:I16) -> -16240.88 | J17: =SUM(J14:J16) -> 0 | K17: =SUM(K14:K16) -> 0 | ... O17: =SUM(O14:O16) -> 0 | Q17: 0
B18: 0.0065 | C18: PIS SOBRE RECEITA FINANCEIRA(0,65%) | D18: =D17*B18 -> -97.37611 | E18: =E17*B18 -> -89.666655 | F18: =F17*0.65% -> -106.68645 | G18: =G17*0.65% -> -75.41664 | H18: =H17*0.65% -> -97.4974 | I18: =I17*0.65% -> -105.56572 | J18: =J17*0.65% -> 0 | K18: =K17*0.65% -> 0 | L18: =L17*0.65% -> 0 | M18: =M17*0.65% -> 0 | ... O18: =O17*0.65% -> 0 | Q18: 0
B19: 0.04 | C19: COFINS SOBRE RECEITA FINANCEIRA (4,00%) | D19: =D17*B19 -> -599.2376 | E19: =E17*B19 -> -551.7948 | F19: =F17*4% -> -656.532 | G19: =G17*4% -> -464.1024 | H19: =H17*4% -> -599.984 | I19: =I17*4% -> -649.6352 | J19: =J17*4% -> 0 | K19: =K17*4% -> 0 | L19: =L17*4% -> 0 | M19: =M17*4% -> 0 | ... O19: =O17*4% -> 0 | Q19: 0
B21: 21131602 | C21: PIS | D21: =D10+D18 -> -842.14767 | E21: =E10+E18 -> -823.23323 | F21: =F10+F18 -> -736.25715 | G21: =G10+G18 -> -1028.6089 | H21: =H10+H18 -> -1619.5732 | I21: =I10+I18 -> -1534.6431 | J21: =J10+J18 -> 0 | K21: =K10+K18 -> 0 | ... O21: =O10+O18 -> 0 | Q21: -1412.7713
B22: 21131601 | C22: COFINS | D22: =D11+D19 -> -4029.7005 | E22: =E11+E19 -> -3930.6469 | F22: =F11+F19 -> -3556.3728 | G22: =G11+G19 -> -4854.5639 | H22: =H11+H19 -> -7610.7575 | I22: =I11+I19 -> -7232.0522 | J22: =J11+J19 -> 0 | K22: =K11+K19 -> 0 | ... O22: =O11+O19 -> 0 | Q22: -6507.31
B24: 11644004 | C24: RETIDOS do Mes PIS | D24: 296.5 | E24: 154.13 | N24: 0
B25: 11644005 | C25: RETIDOS do Mês COFINS | D25: 1368.48 | E25: 848.69 | N25: 0
C27: Compensação Saldo Residual PIS | D27: 545.65 | E27: 669.1 | F27: 736.26 | G27: 0 | H27: 0 | Q27: 0
C28: Compensação Saldo Residual COFINS | D28: 2661.22 | E28: 3081.96 | F28: 3556.37 | G28: 0 | H28: 0 | Q28: 0
B30: 6912 | C30: PIS A RECOLHER | D30: =D21+D24+D27 -> 0.002335 | E30: =E21+E24+E27 -> -0.003225 | F30: =F21+F24+F27 -> 0.00285 | G30: =G21+G24+G27 -> -1028.6089 | H30: =H21+H24+H27 -> -1619.5732 | I30: =I21+I24+I27 -> -1534.6431 | J30: =J21+J24+J27 -> 0 | K30: =K21+K24+K27 -> 0 | ... O30: =O21+O24+O27 -> 0 | Q30: -1412.7713
C31: DARF
D32: =D30+D31 -> 0.002335 | E32: =E30+E31 -> -0.003225 | F32: =F30+F31 -> 0.00285 | G32: =G30+G31 -> -1028.6089 | H32: =H30+H31 -> -1619.5732 | I32: =I30+I31 -> -1534.6431 | J32: =J30+J31 -> 0 | K32: =K30+K31 -> 0 | ... O32: =O30+O31 -> 0 | Q32: -1412.7713
B34: 5856 | C34: COFINS A RECOLHER | D34: =D22+D25+D28 -> -0.00052 | E34: =E22+E25+E28 -> 0.00312 | F34: =F22+F25+F28 -> -0.0028 | G34: =G22+G25+G28 -> -4854.5639 | H34: =H22+H25+H28 -> -7610.7575 | I34: =I22+I25+I28 -> -7232.0522 | J34: =J22+J25+J28 -> 0 | K34: =K22+K25+K28 -> 0 | ... O34: =O22+O25+O28 -> 0 | Q34: -6507.31
C35: DARF
D36: =D34+D35 -> -0.00052 | E36: =E34+E35 -> 0.00312 | F36: =F34+F35 -> -0.0028 | G36: =G34+G35 -> -4854.5639 | H36: =H34+H35 -> -7610.7575 | I36: =I34+I35 -> -7232.0522 | J36: =J34+J35 -> 0 | K36: =K34+K35 -> 0 | ... O36: =O34+O35 -> 0 | Q36: -6507.31
C38: CONTABILIZAÇÃO
B39: 21131602 | C39: PIS/PASEP A RECOLHER | D39: =IFERROR(VLOOKUP(B39,'Bal 012026'!B:H,7,0),0) -> -842.15 | E39: =IFERROR(VLOOKUP($B$39,'Bal 022026'!$B:$H,7,0),0) -> -154.13 | F39: =IFERROR(VLOOKUP(B39,'Bal 032026'!$B:$H,7,0),0) -> 736.26 | G39: =IFERROR(VLOOKUP(B39,'Bal 042026'!B:H,7,0),0) -> -1028.61 | H39: =IFERROR(VLOOKUP(B39,'Bal 052026'!B:H,7,0),0) -> -1619.57 | I39: =IFERROR(VLOOKUP($B$39,'Bal 06.2026'!B:H,7,0),0) -> 0 | J39: =IFERROR(VLOOKUP(B39,'Bal 07.2026'!A:G,7,0),0) -> 0 | K39: =IFERROR(VLOOKUP(B39,'Bal 08.2026'!A:G,7,0),0) -> 0 | L39: =IFERROR(VLOOKUP(B39,'Bal 09.2026'!A:G,7,0),0) -> 0 | M39: =IFERROR(VLOOKUP(B39,'Bal 10.2026'!A:G,7,0),0) -> 0 | N39: =IFERROR(VLOOKUP(B39,'Bal 11.2026'!A:G,7,0),0) -> 0 | O39: =IFERROR(VLOOKUP(B39,'Bal 12.2026'!A:G,7,0),0) -> 0 | Q39: 0
B40: 21131601 | C40: COFINS A RECOLHER | D40: =IFERROR(VLOOKUP(B40,'Bal 012026'!B:H,7,0),0) -> -4029.7 | E40: =IFERROR(VLOOKUP($B$40,'Bal 022026'!$B:$H,7,0),0) -> -848.69 | F40: =IFERROR(VLOOKUP(B40,'Bal 032026'!$B:$H,7,0),0) -> 3556.37 | G40: =IFERROR(VLOOKUP(B40,'Bal 042026'!B:H,7,0),0) -> -4854.56 | H40: =IFERROR(VLOOKUP(B40,'Bal 052026'!B:H,7,0),0) -> -7610.76 | I40: =IFERROR(VLOOKUP($B$39,'Bal 06.2026'!B:H,7,0),0) -> 0 | J40: =IFERROR(VLOOKUP(B40,'Bal 07.2026'!A:G,7,0),0) -> 0 | K40: =IFERROR(VLOOKUP(B40,'Bal 08.2026'!A:G,7,0),0) -> 0 | L40: =IFERROR(VLOOKUP(B40,'Bal 09.2026'!A:G,7,0),0) -> 0 | M40: =IFERROR(VLOOKUP(B40,'Bal 10.2026'!A:G,7,0),0) -> 0 | N40: =IFERROR(VLOOKUP(B40,'Bal 11.2026'!A:G,7,0),0) -> 0 | O40: =IFERROR(VLOOKUP(B40,'Bal 12.2026'!A:G,7,0),0) -> 0 | Q40: 0
C41: Check | E41: =E21-E39 -> -669.10323 | F41: =F21+F39 -> 0.00285 | G41: =G21-G39 -> 0.001065 | H41: =H21-H39 -> -0.00323
E42: =E22-E40 -> -3081.9569 | F42: =F22+F40 -> -0.0028 | G42: =G22-G40 -> -0.00388 | H42: =H22-H40 -> 0.00248

Sheet Bal 06.2026
B1: Table
C2: Exercício/período | D2: 006.2026 | E2: 006.2026 | F2: 006.2026 | G2: 006.2026 | H2: 006.2026
B3: Conta do Razão | D3: Saldo Anterior | E3: Débitos | F3: Créditos | G3: Movimento | H3: Saldo Acumulado
A4: =IF(LEN(B4)=8,LEFT(B4,1),0) -> 0 | B4: G517 | C4: PLANO DE CONTAS CONS | D4: -0.02 | E4: 682875.25 | F4: 682875.23 | G4: 0.02 | H4: 0
A5: =IF(LEN(B5)=8,LEFT(B5,1),0) -> 0 | B5: G5171 | C5: ATIVO | D5: 2910168.8 | E5: 485093.34 | F5: 441370.95 | G5: 43722.39 | H5: 2953891.1
A6: =IF(LEN(B6)=8,LEFT(B6,1),0) -> 0 | B6: G51711 | C6: CIRCULANTE | D6: 2587946.5 | E6: 484564.66 | F6: 429731.16 | G6: 54833.5 | H6: 2642780
A7: =IF(LEN(B7)=8,LEFT(B7,1),0) -> 0 | B7: G517111 | C7: DISPONÍVEL | D7: 205461.79 | E7: 359433.77 | F7: 314727.93 | G7: 44705.84 | H7: 250167.63
A8: =IF(LEN(B8)=8,LEFT(B8,1),0) -> G | B8: G5171113 | C8: BANCOS CONTA DEPÓSIT | D8: 205461.79 | E8: 359433.77 | F8: 314727.93 | G8: 44705.84 | H8: 250167.63
A9: =IF(LEN(B9)=8,LEFT(B9,1),0) -> 0 | B9: G51711131 | C9: BANCOS CONTA DEPÓSIT | D9: 205461.79 | E9: 359433.77 | F9: 314727.93 | G9: 44705.84 | H9: 250167.63
A10: =IF(LEN(B10)=8,LEFT(B10,1),0) -> 1 | B10: 11131050 | C10: BCO SANTANDER | D10: 71087.8 | E10: 20325.44 | F10: 50552 | G10: -30226.56 | H10: 40861.24
A11: =IF(LEN(B11)=8,LEFT(B11,1),0) -> 1 | B11: 11131090 | C11: BANCO SANTANDER | D11: 118258.02 | E11: 63877.81 | F11: 240.1 | G11: 63637.71 | H11: 181895.73
A12: =IF(LEN(B12)=8,LEFT(B12,1),0) -> 1 | B12: 11131091 | C12: BANCO SANTANDER | D12: 16508.35 | E12: 11100.68 | F12: 198.37 | G12: 10902.31 | H12: 27410.66
A13: =IF(LEN(B13)=8,LEFT(B13,1),0) -> 1 | B13: 11132050 | C13: BCO SANTANDER | D13: 0 | E13: 33942.06 | F13: 33942.06 | G13: 0 | H13: 0
A14: =IF(LEN(B14)=8,LEFT(B14,1),0) -> 1 | B14: 11132090 | C14: BANCO SANTANDER | D14: -392.38 | E14: 107071.42 | F14: 106679.04 | G14: 392.38 | H14: 0
A15: =IF(LEN(B15)=8,LEFT(B15,1),0) -> 1 | B15: 11132091 | C15: BANCO SANTANDER | D15: 0 | E15: 22201.36 | F15: 22201.36 | G15: 0 | H15: 0
A16: =IF(LEN(B16)=8,LEFT(B16,1),0) -> 1 | B16: 11133050 | C16: BCO SANTANDER SAIDA | D16: 0 | E16: 100915 | F16: 100915 | G16: 0 | H16: 0
A17: =IF(LEN(B17)=8,LEFT(B17,1),0) -> 0 | B17: G517112 | C17: APLICAÇÕES | D17: 616021.84 | E17: 6936.26 | F17: 0 | G17: 6936.26 | H17: 622958.1
A18: =IF(LEN(B18)=8,LEFT(B18,1),0) -> G | B18: G5171126 | C18: QUOTAS DE FUNDOS DE | D18: 616021.84 | E18: 6936.26 | F18: 0 | G18: 6936.26 | H18: 622958.1
A19: =IF(LEN(B19)=8,LEFT(B19,1),0) -> 0 | B19: G51711261 | C19: VINCULADAS À COBERTU | D19: 616021.84 | E19: 6936.26 | F19: 0 | G19: 6936.26 | H19: 622958.1
A20: =IF(LEN(B20)=8,LEFT(B20,1),0) -> 0 | B20: G517112612 | C20: QUOTAS DE OUTROS FUN | D20: 616021.84 | E20: 6936.26 | F20: 0 | G20: 6936.26 | H20: 622958.1
A21: =IF(LEN(B21)=8,LEFT(B21,1),0) -> 0 | B21: G5171126121 | C21: VALOR ORIGINAL | D21: 616021.84 | E21: 6936.26 | F21: 0 | G21: 6936.26 | H21: 622958.1
A22: =IF(LEN(B22)=8,LEFT(B22,1),0) -> 1 | B22: 11240001 | C22: FD ÑEX CUV VC CP DPV | D22: 616021.84 | E22: 6936.26 | F22: 0 | G22: 6936.26 | H22: 622958.1
A23: =IF(LEN(B23)=8,LEFT(B23,1),0) -> 0 | B23: G517113 | C23: CRÉDITOS DAS OPERAÇÕ | D23: 41642 | E23: 97558.95 | F23: 96588.65 | G23: 970.3 | H23: 42612.3
A24: =IF(LEN(B24)=8,LEFT(B24,1),0) -> G | B24: G5171131 | C24: PRÊMIOS A RECEBER | D24: 41642 | E24: 96735.3 | F24: 95765 | G24: 970.3 | H24: 42612.3
A25: =IF(LEN(B25)=8,LEFT(B25,1),0) -> 0 | B25: G51711311 | C25: DIRETO | D25: 41642 | E25: 96735.3 | F25: 95765 | G25: 970.3 | H25: 42612.3
A26: =IF(LEN(B26)=8,LEFT(B26,1),0) -> 0 | B26: G517113111 | C26: PRÊMIOS - RISCOS VIG | D26: 41642 | E26: 96735.3 | F26: 95765 | G26: 970.3 | H26: 42612.3
A27: =IF(LEN(B27)=8,LEFT(B27,1),0) -> 1 | B27: 11311011 | C27: SOMPO SEG REC RECEIT | D27: 0 | E27: 17447.3 | F27: 16576 | G27: 871.3 | H27: 871.3
A28: =IF(LEN(B28)=8,LEFT(B28,1),0) -> 1 | B28: 11311094 | C28: Clientes SompoRisk | D28: 41642 | E28: 79288 | F28: 79189 | G28: 99 | H28: 41741
A29: =IF(LEN(B29)=8,LEFT(B29,1),0) -> G | B29: G5171138 | C29: OUTROS CRÉDITOS OPER | D29: 0 | E29: 823.65 | F29: 823.65 | G29: 0 | H29: 0
A30: =IF(LEN(B30)=8,LEFT(B30,1),0) -> 0 | B30: G51711388 | C30: OUTROS CRÉDITOS | D30: 0 | E30: 823.65 | F30: 823.65 | G30: 0 | H30: 0
A31: =IF(LEN(B31)=8,LEFT(B31,1),0) -> 1 | B31: 11391004 | C31: SALVADO VEND RECEBER | D31: 0 | E31: 388 | F31: 388 | G31: 0 | H31: 0
A32: =IF(LEN(B32)=8,LEFT(B32,1),0) -> 1 | B32: 11391098 | C32: CRED OPR CONCILIAÇÃO | D32: 0 | E32: 435.65 | F32: 435.65 | G32: 0 | H32: 0
A33: =IF(LEN(B33)=8,LEFT(B33,1),0) -> 0 | B33: G517114 | C33: TÍTULOS E CRÉDITOS A | D33: 1724820.9 | E33: 20635.68 | F33: 18414.58 | G33: 2221.1 | H33: 1727042
A34: =IF(LEN(B34)=8,LEFT(B34,1),0) -> G | B34: G5171141 | C34: CRÉDITOS A RECEBER | D34: 148524.51 | E34: 7391.75 | F34: 9184.25 | G34: -1792.5 | H34: 146732.01
A35: =IF(LEN(B35)=8,LEFT(B35,1),0) -> 0 | B35: G51711418 | C35: OUTROS CRÉDITOS A RE | D35: 148524.51 | E35: 7391.75 | F35: 9184.25 | G35: -1792.5 | H35: 146732.01
A36: =IF(LEN(B36)=8,LEFT(B36,1),0) -> 1 | B36: 11610099 | C36: OUTROS CRÉD.RECEBER | D36: 148524.51 | E36: 7391.75 | F36: 9184.25 | G36: -1792.5 | H36: 146732.01
A37: =IF(LEN(B37)=8,LEFT(B37,1),0) -> G | B37: G5171144 | C37: CRÉDITOS TRIBUTÁRIOS | D37: 1576296.4 | E37: 13243.93 | F37: 9230.33 | G37: 4013.6 | H37: 1580310
A38: =IF(LEN(B38)=8,LEFT(B38,1),0) -> 0 | B38: G51711441 | C38: CRÉDITOS DE IMPOSTO | D38: 555471.6 | E38: 990.51 | F38: 0 | G38: 990.51 | H38: 556462.11
A39: =IF(LEN(B39)=8,LEFT(B39,1),0) -> 0 | B39: G517114411 | C39: IMPOSTO DE RENDA A C | D39: 555471.6 | E39: 990.51 | F39: 0 | G39: 990.51 | H39: 556462.11
A40: =IF(LEN(B40)=8,LEFT(B40,1),0) -> 1 | B40: 11641001 | C40: IRPJ A COMPENSAR CP | D40: 106126.2 | E40: 990.51 | F40: 0 | G40: 990.51 | H40: 107116.71
A41: =IF(LEN(B41)=8,LEFT(B41,1),0) -> 1 | B41: 11641008 | C41: IR RETIDO S/APL FIN | D41: 449345.4 | E41: 0 | F41: 0 | G41: 0 | H41: 449345.4
A42: =IF(LEN(B42)=8,LEFT(B42,1),0) -> 0 | B42: G51711442 | C42: CRÉDITOS DE CONTRIBU | D42: 842679.19 | E42: 7848.07 | F42: 0 | G42: 7848.07 | H42: 850527.26
A43: =IF(LEN(B43)=8,LEFT(B43,1),0) -> 0 | B43: G517114421 | C43: CONTRIBUIÇÃO SOCIAL | D43: 775367.41 | E43: 6976.93 | F43: 0 | G43: 6976.93 | H43: 782344.34
A44: =IF(LEN(B44)=8,LEFT(B44,1),0) -> 1 | B44: 11642001 | C44: CSLL A COMPENSAR CP | D44: 775367.41 | E44: 6976.93 | F44: 0 | G44: 6976.93 | H44: 782344.34
A45: =IF(LEN(B45)=8,LEFT(B45,1),0) -> 0 | B45: G517114425 | C45: AJUSTES TEMPORAIS | D45: 67311.78 | E45: 871.14 | F45: 0 | G45: 871.14 | H45: 68182.92
A46: =IF(LEN(B46)=8,LEFT(B46,1),0) -> 1 | B46: 11642005 | C46: CSLL RETIDO A COMP | D46: 67311.78 | E46: 871.14 | F46: 0 | G46: 871.14 | H46: 68182.92
A47: =IF(LEN(B47)=8,LEFT(B47,1),0) -> 0 | B47: G51711445 | C47: CRÉDITOS DE COFINS E | D47: 80290.34 | E47: 3179.59 | F47: 9230.33 | G47: -6050.74 | H47: 74239.6
A48: =IF(LEN(B48)=8,LEFT(B48,1),0) -> 0 | B48: G517114451 | C48: COFINS A COMPENSAR | D48: 66190.47 | E48: 2613.33 | F48: 7610.76 | G48: -4997.43 | H48: 61193.04
A49: =IF(LEN(B49)=8,LEFT(B49,1),0) -> 1 | B49: 11644005 | C49: COFINS RETIDO A COMP | D49: 66190.47 | E49: 2613.33 | F49: 7610.76 | G49: -4997.43 | H49: 61193.04
A50: =IF(LEN(B50)=8,LEFT(B50,1),0) -> 0 | B50: G517114453 | C50: PIS A COMPENSAR | D50: 14099.87 | E50: 566.26 | F50: 1619.57 | G50: -1053.31 | H50: 13046.56
A51: =IF(LEN(B51)=8,LEFT(B51,1),0) -> 1 | B51: 11644004 | C51: PIS RETIDO A COMP | D51: 14099.87 | E51: 566.26 | F51: 1619.57 | G51: -1053.31 | H51: 13046.56
A52: =IF(LEN(B52)=8,LEFT(B52,1),0) -> 0 | B52: G51711448 | C52: OUTROS CRÉDITOS TRIB | D52: 97855.24 | E52: 1225.76 | F52: 0 | G52: 1225.76 | H52: 99081
A53: =IF(LEN(B53)=8,LEFT(B53,1),0) -> 1 | B53: 11641009 | C53: IR RETIDO SERV PREST | D53: 97855.24 | E53: 1225.76 | F53: 0 | G53: 1225.76 | H53: 99081
A54: =IF(LEN(B54)=8,LEFT(B54,1),0) -> 0 | B54: G51712 | C54: ATIVO NÃO CIRCULANTE | D54: 322222.24 | E54: 528.68 | F54: 11639.79 | G54: -11111.11 | H54: 311111.13
A55: =IF(LEN(B55)=8,LEFT(B55,1),0) -> 0 | B55: G517121 | C55: REALIZÁVEL A LONGO P | D55: 322222.24 | E55: 528.68 | F55: 11639.79 | G55: -11111.11 | H55: 311111.13
A56: =IF(LEN(B56)=8,LEFT(B56,1),0) -> G | B56: G5171213 | C56: TÍTULOS E CRÉDITOS A | D56: 322222.24 | E56: 528.68 | F56: 11639.79 | G56: -11111.11 | H56: 311111.13
A57: =IF(LEN(B57)=8,LEFT(B57,1),0) -> 0 | B57: G51712131 | C57: CRÉDITOS A RECEBER | D57: 322222.24 | E57: 528.68 | F57: 11639.79 | G57: -11111.11 | H57: 311111.13
A58: =IF(LEN(B58)=8,LEFT(B58,1),0) -> 0 | B58: G517121311 | C58: CRÉDITOS A RECEBER | D58: 322222.24 | E58: 528.68 | F58: 11639.79 | G58: -11111.11 | H58: 311111.13
A59: =IF(LEN(B59)=8,LEFT(B59,1),0) -> 1 | B59: 12610001 | C59: CRÉDITOS RECEBER-LP | D59: 322222.24 | E59: 528.68 | F59: 11639.79 | G59: -11111.11 | H59: 311111.13
A60: =IF(LEN(B60)=8,LEFT(B60,1),0) -> 0 | B60: G517123 | C60: IMOBILIZADO | D60: 0 | E60: 0 | F60: 0 | G60: 0 | H60: 0
A61: =IF(LEN(B61)=8,LEFT(B61,1),0) -> G | B61: G5171232 | C61: EQUIPAMENTOS | D61: 0 | E61: 0 | F61: 0 | G61: 0 | H61: 0
A62: =IF(LEN(B62)=8,LEFT(B62,1),0) -> 0 | B62: G51712321 | C62: INFORMÁTICA | D62: 16679.39 | E62: 0 | F62: 0 | G62: 0 | H62: 16679.39
A63: =IF(LEN(B63)=8,LEFT(B63,1),0) -> 0 | B63: G517123211 | C63: HARDWARE | D63: 16679.39 | E63: 0 | F63: 0 | G63: 0 | H63: 16679.39
A64: =IF(LEN(B64)=8,LEFT(B64,1),0) -> 1 | B64: 14221001 | C64: EQTOS DE INFORMATICA | D64: 16679.39 | E64: 0 | F64: 0 | G64: 0 | H64: 16679.39
A65: =IF(LEN(B65)=8,LEFT(B65,1),0) -> 0 | B65: G51712322 | C65: TELECOMUNICAÇÕES | D65: 6147 | E65: 0 | F65: 0 | G65: 0 | H65: 6147
A66: =IF(LEN(B66)=8,LEFT(B66,1),0) -> 1 | B66: 14222001 | C66: TELECOMUNICAÇÕES | D66: 6147 | E66: 0 | F66: 0 | G66: 0 | H66: 6147
A67: =IF(LEN(B67)=8,LEFT(B67,1),0) -> 0 | B67: G51712329 | C67: DEPRECIAÇÃO ACUMULAD | D67: -22826.39 | E67: 0 | F67: 0 | G67: 0 | H67: -22826.39
A68: =IF(LEN(B68)=8,LEFT(B68,1),0) -> 0 | B68: G517123291 | C68: DEPRECIAÇÃO ACUMULAD | D68: -22826.39 | E68: 0 | F68: 0 | G68: 0 | H68: -22826.39
A69: =IF(LEN(B69)=8,LEFT(B69,1),0) -> 1 | B69: 14229001 | C69: DEP.ACUM EQTO INFORM | D69: -16679.39 | E69: 0 | F69: 0 | G69: 0 | H69: -16679.39
A70: =IF(LEN(B70)=8,LEFT(B70,1),0) -> 1 | B70: 14229003 | C70: DEP.ACUM TELECOMUNIC | D70: -6147 | E70: 0 | F70: 0 | G70: 0 | H70: -6147
A71: =IF(LEN(B71)=8,LEFT(B71,1),0) -> 0 | B71: G5172 | C71: PASSIVO | D71: -2801920.4 | E71: 129554.5 | F71: 125026.99 | G71: 4527.51 | H71: -2797392.9
A72: =IF(LEN(B72)=8,LEFT(B72,1),0) -> 0 | B72: G51721 | C72: CIRCULANTE | D72: -188704.13 | E72: 129554.5 | F72: 125026.99 | G72: 4527.51 | H72: -184176.62
A73: =IF(LEN(B73)=8,LEFT(B73,1),0) -> 0 | B73: G517211 | C73: CONTAS A PAGAR | D73: -188704.13 | E73: 129554.5 | F73: 125026.99 | G73: 4527.51 | H73: -184176.62
A74: =IF(LEN(B74)=8,LEFT(B74,1),0) -> G | B74: G5172111 | C74: OBRIGAÇÕES A PAGAR | D74: -158237.57 | E74: 98494.08 | F74: 119161.82 | G74: -20667.74 | H74: -178905.31
A75: =IF(LEN(B75)=8,LEFT(B75,1),0) -> 0 | B75: G51721111 | C75: FORNECEDORES | D75: -144244.55 | E75: 85524.33 | F75: 61044.68 | G75: 24479.65 | H75: -119764.9
A76: =IF(LEN(B76)=8,LEFT(B76,1),0) -> 2 | B76: 21111001 | C76: FORN BENS SERVIÇOS | D76: -115916.53 | E76: 51760.66 | F76: 55609.03 | G76: -3848.37 | H76: -119764.9
A77: =IF(LEN(B77)=8,LEFT(B77,1),0) -> 2 | B77: 21111002 | C77: PROV FORNECEDOR CP | D77: -28328.02 | E77: 33763.67 | F77: 5435.65 | G77: 28328.02 | H77: 0
A78: =IF(LEN(B78)=8,LEFT(B78,1),0) -> 0 | B78: G51721119 | C78: OUTRAS OBRIGAÇÕES A | D78: -13993.02 | E78: 12969.75 | F78: 58117.14 | G78: -45147.39 | H78: -59140.41
A79: =IF(LEN(B79)=8,LEFT(B79,1),0) -> 0 | B79: G517211198 | C79: OUTRAS OBRIGAÇÕES | D79: -13993.02 | E79: 12969.75 | F79: 58117.14 | G79: -45147.39 | H79: -59140.41
A80: =IF(LEN(B80)=8,LEFT(B80,1),0) -> 2 | B80: 21111099 | C80: OUTRAS OBRIG.PAGAR | D80: -13993.02 | E80: 12969.75 | F80: 58117.14 | G80: -45147.39 | H80: -59140.41
A81: =IF(LEN(B81)=8,LEFT(B81,1),0) -> G | B81: G5172112 | C81: IMPOSTOS E ENCARGOS | D81: -13248.73 | E81: 13842.59 | F81: 5865.17 | G81: 7977.42 | H81: -5271.31
A82: =IF(LEN(B82)=8,LEFT(B82,1),0) -> 0 | B82: G51721122 | C82: IMPOSTO DE RENDA RET | D82: 0 | E82: 0 | F82: 420.38 | G82: -420.38 | H82: -420.38
A83: =IF(LEN(B83)=8,LEFT(B83,1),0) -> 2 | B83: 21131104 | C83: IRF TERCEIROS RECOL | D83: 0 | E83: 0 | F83: 420.38 | G83: -420.38 | H83: -420.38
A84: =IF(LEN(B84)=8,LEFT(B84,1),0) -> 0 | B84: G51721128 | C84: OUTROS IMPOSTOS E EN | D84: -13248.73 | E84: 13842.59 | F84: 5444.79 | G84: 8397.8 | H84: -4850.93
A85: =IF(LEN(B85)=8,LEFT(B85,1),0) -> 2 | B85: 21131601 | C85: COFINS A RECOLHER | D85: -7610.76 | E85: 7610.76 | F85: 0 | G85: 7610.76 | H85: 0
A86: =IF(LEN(B86)=8,LEFT(B86,1),0) -> 2 | B86: 21131602 | C86: PIS/PASEP A RECOLHER | D86: -1619.57 | E86: 1619.57 | F86: 0 | G86: 1619.57 | H86: 0
A87: =IF(LEN(B87)=8,LEFT(B87,1),0) -> 2 | B87: 21131701 | C87: PIS/COFINS/CSLL TERC | D87: 0 | E87: 0 | F87: 1303.16 | G87: -1303.16 | H87: -1303.16
A88: =IF(LEN(B88)=8,LEFT(B88,1),0) -> 2 | B88: 21133102 | C88: ISS S/FATURAMENTO | D88: -4018.4 | E88: 4612.26 | F88: 4141.63 | G88: 470.63 | H88: -3547.77
A89: =IF(LEN(B89)=8,LEFT(B89,1),0) -> G | B89: G5172116 | C89: IMPOSTOS E CONTRIBUI | D89: -17217.83 | E89: 17217.83 | F89: 0 | G89: 17217.83 | H89: 0
A90: =IF(LEN(B90)=8,LEFT(B90,1),0) -> 0 | B90: G51721161 | C90: IMPOSTO DE RENDA | D90: -12130.76 | E90: 12130.76 | F90: 0 | G90: 12130.76 | H90: 0
A91: =IF(LEN(B91)=8,LEFT(B91,1),0) -> 0 | B91: G517211611 | C91: IMPOSTO DE RENDA | D91: -27215.28 | E91: 0 | F91: 0 | G91: 0 | H91: -27215.28
A92: =IF(LEN(B92)=8,LEFT(B92,1),0) -> 2 | B92: 21131101 | C92: PROVISÃO PARA IRPJ | D92: -27215.28 | E92: 0 | F92: 0 | G92: 0 | H92: -27215.28
A93: =IF(LEN(B93)=8,LEFT(B93,1),0) -> 0 | B93: G517211612 | C93: (-) ANTECIPAÇÃO DE I | D93: 15084.52 | E93: 12130.76 | F93: 0 | G93: 12130.76 | H93: 27215.28
A94: =IF(LEN(B94)=8,LEFT(B94,1),0) -> 2 | B94: 21131102 | C94: (-) ANTECIPACAO IRPJ | D94: 15084.52 | E94: 12130.76 | F94: 0 | G94: 12130.76 | H94: 27215.28
A95: =IF(LEN(B95)=8,LEFT(B95,1),0) -> 0 | B95: G51721162 | C95: CONTRIBUIÇÃO SOCIAL | D95: -5087.07 | E95: 5087.07 | F95: 0 | G95: 5087.07 | H95: 0
A96: =IF(LEN(B96)=8,LEFT(B96,1),0) -> 0 | B96: G517211621 | C96: CONTRIBUIÇÃO SOCIAL | D96: -13397.5 | E96: 0 | F96: 0 | G96: 0 | H96: -13397.5
A97: =IF(LEN(B97)=8,LEFT(B97,1),0) -> 2 | B97: 21131201 | C97: PROVISÃO PARA CSLL | D97: -13397.5 | E97: 0 | F97: 0 | G97: 0 | H97: -13397.5
A98: =IF(LEN(B98)=8,LEFT(B98,1),0) -> 0 | B98: G517211622 | C98: (-) ANTECIPAÇÃO DE C | D98: 8310.43 | E98: 5087.07 | F98: 0 | G98: 5087.07 | H98: 13397.5
A99: =IF(LEN(B99)=8,LEFT(B99,1),0) -> 2 | B99: 21131202 | C99: (-) ANTECIPAÇÃO CSLL | D99: 8310.43 | E99: 5087.07 | F99: 0 | G99: 5087.07 | H99: 13397.5
A100: =IF(LEN(B100)=8,LEFT(B100,1),0) -> 0 | B100: G51724 | C100: PATRIMÔNIO LÍQUIDO O | D100: -2613216.3 | E100: 0 | F100: 0 | G100: 0 | H100: -2613216.3
...

Sheet Bal 052026
B1: Table
C2: Exercício/período | D2: 005.2026 | E2: 005.2026 | F2: 005.2026 | G2: 005.2026 | H2: 005.2026
B3: Conta do Razão | D3: Saldo Anterior | E3: Débitos | F3: Créditos | G3: Movimento | H3: Saldo Acumulado
A4: =IF(LEN(B4)=8,LEFT(B4,1),0) -> 0 | B4: G517 | C4: PLANO DE CONTAS CONS | D4: 0 | E4: 616146.83 | F4: 616146.85 | G4: -0.02 | H4: -0.02
A5: =IF(LEN(B5)=8,LEFT(B5,1),0) -> 0 | B5: G5171 | C5: ATIVO | D5: 2822575 | E5: 477901.29 | F5: 390307.52 | G5: 87593.77 | H5: 2910168.8
A6: =IF(LEN(B6)=8,LEFT(B6,1),0) -> 0 | B6: G51711 | C6: CIRCULANTE | D6: 2489241.6 | E6: 477372.61 | F6: 378667.73 | G6: 98704.88 | H6: 2587946.5
A7: =IF(LEN(B7)=8,LEFT(B7,1),0) -> 0 | B7: G517111 | C7: DISPONÍVEL | D7: 119524.75 | E7: 331796.44 | F7: 245859.4 | G7: 85937.04 | H7: 205461.79
A8: =IF(LEN(B8)=8,LEFT(B8,1),0) -> G | B8: G5171113 | C8: BANCOS CONTA DEPÓSIT | D8: 119524.75 | E8: 331796.44 | F8: 245859.4 | G8: 85937.04 | H8: 205461.79
A9: =IF(LEN(B9)=8,LEFT(B9,1),0) -> 0 | B9: G51711131 | C9: BANCOS CONTA DEPÓSIT | D9: 119524.75 | E9: 331796.44 | F9: 245859.4 | G9: 85937.04 | H9: 205461.79
A10: =IF(LEN(B10)=8,LEFT(B10,1),0) -> 1 | B10: 11131050 | C10: BCO SANTANDER | D10: 57128.19 | E10: 27127.42 | F10: 13167.81 | G10: 13959.61 | H10: 71087.8
A11: =IF(LEN(B11)=8,LEFT(B11,1),0) -> 1 | B11: 11131090 | C11: BANCO SANTANDER | D11: 62805.43 | E11: 55683.79 | F11: 231.2 | G11: 55452.59 | H11: 118258.02
A12: =IF(LEN(B12)=8,LEFT(B12,1),0) -> 1 | B12: 11131091 | C12: BANCO SANTANDER | D12: 1 | E12: 16878.02 | F12: 370.67 | G12: 16507.35 | H12: 16508.35
A13: =IF(LEN(B13)=8,LEFT(B13,1),0) -> 1 | B13: 11132010 | C13: E341CC0008417/001791 | D13: 0 | E13: 99.56 | F13: 99.56 | G13: 0 | H13: 0
A14: =IF(LEN(B14)=8,LEFT(B14,1),0) -> 1 | B14: 11132050 | C14: BCO SANTANDER | D14: 0 | E14: 45503.48 | F14: 45503.48 | G14: 0 | H14: 0
A15: =IF(LEN(B15)=8,LEFT(B15,1),0) -> 1 | B15: 11132090 | C15: BANCO SANTANDER | D15: -409.87 | E15: 108364.88 | F15: 108347.39 | G15: 17.49 | H15: -392.38
A16: =IF(LEN(B16)=8,LEFT(B16,1),0) -> 1 | B16: 11132091 | C16: BANCO SANTANDER | D16: 0 | E16: 33757.5 | F16: 33757.5 | G16: 0 | H16: 0
A17: =IF(LEN(B17)=8,LEFT(B17,1),0) -> 1 | B17: 11133050 | C17: BCO SANTANDER SAIDA | D17: 0 | E17: 41493.36 | F17: 41493.36 | G17: 0 | H17: 0
A18: =IF(LEN(B18)=8,LEFT(B18,1),0) -> 1 | B18: 11133090 | C18: BANCO SANTANDER | D18: 0 | E18: 2888.43 | F18: 2888.43 | G18: 0 | H18: 0
A19: =IF(LEN(B19)=8,LEFT(B19,1),0) -> 0 | B19: G517112 | C19: APLICAÇÕES | D19: 614908.77 | E19: 6759.61 | F19: 5646.54 | G19: 1113.07 | H19: 616021.84
A20: =IF(LEN(B20)=8,LEFT(B20,1),0) -> G | B20: G5171126 | C20: QUOTAS DE FUNDOS DE | D20: 614908.77 | E20: 6759.61 | F20: 5646.54 | G20: 1113.07 | H20: 616021.84
A21: =IF(LEN(B21)=8,LEFT(B21,1),0) -> 0 | B21: G51711261 | C21: VINCULADAS À COBERTU | D21: 614908.77 | E21: 6759.61 | F21: 5646.54 | G21: 1113.07 | H21: 616021.84
A22: =IF(LEN(B22)=8,LEFT(B22,1),0) -> 0 | B22: G517112612 | C22: QUOTAS DE OUTROS FUN | D22: 614908.77 | E22: 6759.61 | F22: 5646.54 | G22: 1113.07 | H22: 616021.84
A23: =IF(LEN(B23)=8,LEFT(B23,1),0) -> 0 | B23: G5171126121 | C23: VALOR ORIGINAL | D23: 614908.77 | E23: 6759.61 | F23: 5646.54 | G23: 1113.07 | H23: 616021.84
A24: =IF(LEN(B24)=8,LEFT(B24,1),0) -> 1 | B24: 11240001 | C24: FD ÑEX CUV VC CP DPV | D24: 614908.77 | E24: 6759.61 | F24: 5646.54 | G24: 1113.07 | H24: 616021.84
A25: =IF(LEN(B25)=8,LEFT(B25,1),0) -> 0 | B25: G517113 | C25: CRÉDITOS DAS OPERAÇÕ | D25: 33118.5 | E25: 113299.57 | F25: 104776.07 | G25: 8523.5 | H25: 41642
A26: =IF(LEN(B26)=8,LEFT(B26,1),0) -> G | B26: G5171131 | C26: PRÊMIOS A RECEBER | D26: 33118.5 | E26: 87676.57 | F26: 79153.07 | G26: 8523.5 | H26: 41642
A27: =IF(LEN(B27)=8,LEFT(B27,1),0) -> 0 | B27: G51711311 | C27: DIRETO | D27: 33118.5 | E27: 87676.57 | F27: 79153.07 | G27: 8523.5 | H27: 41642
A28: =IF(LEN(B28)=8,LEFT(B28,1),0) -> 0 | B28: G517113111 | C28: PRÊMIOS - RISCOS VIG | D28: 33118.5 | E28: 87676.57 | F28: 79153.07 | G28: 8523.5 | H28: 41642
A29: =IF(LEN(B29)=8,LEFT(B29,1),0) -> 1 | B29: 11311011 | C29: SOMPO SEG REC RECEIT | D29: 0 | E29: 23127.07 | F29: 23127.07 | G29: 0 | H29: 0
A30: =IF(LEN(B30)=8,LEFT(B30,1),0) -> 1 | B30: 11311094 | C30: Clientes SompoRisk | D30: 33118.5 | E30: 64549.5 | F30: 56026 | G30: 8523.5 | H30: 41642
A31: =IF(LEN(B31)=8,LEFT(B31,1),0) -> G | B31: G5171138 | C31: OUTROS CRÉDITOS OPER | D31: 0 | E31: 25623 | F31: 25623 | G31: 0 | H31: 0
A32: =IF(LEN(B32)=8,LEFT(B32,1),0) -> 0 | B32: G51711388 | C32: OUTROS CRÉDITOS | D32: 0 | E32: 25623 | F32: 25623 | G32: 0 | H32: 0
A33: =IF(LEN(B33)=8,LEFT(B33,1),0) -> 1 | B33: 11391004 | C33: SALVADO VEND RECEBER | D33: 0 | E33: 25623 | F33: 25623 | G33: 0 | H33: 0
A34: =IF(LEN(B34)=8,LEFT(B34,1),0) -> 0 | B34: G517114 | C34: TÍTULOS E CRÉDITOS A | D34: 1721689.6 | E34: 25516.99 | F34: 22385.72 | G34: 3131.27 | H34: 1724820.9
A35: =IF(LEN(B35)=8,LEFT(B35,1),0) -> G | B35: G5171141 | C35: CRÉDITOS A RECEBER | D35: 158402.54 | E35: 6624.52 | F35: 16502.55 | G35: -9878.03 | H35: 148524.51
A36: =IF(LEN(B36)=8,LEFT(B36,1),0) -> 0 | B36: G51711418 | C36: OUTROS CRÉDITOS A RE | D36: 158402.54 | E36: 6624.52 | F36: 16502.55 | G36: -9878.03 | H36: 148524.51
A37: =IF(LEN(B37)=8,LEFT(B37,1),0) -> 1 | B37: 11610099 | C37: OUTROS CRÉD.RECEBER | D37: 158402.54 | E37: 6624.52 | F37: 16502.55 | G37: -9878.03 | H37: 148524.51
A38: =IF(LEN(B38)=8,LEFT(B38,1),0) -> G | B38: G5171144 | C38: CRÉDITOS TRIBUTÁRIOS | D38: 1563287.1 | E38: 18892.47 | F38: 5883.17 | G38: 13009.3 | H38: 1576296.4
A39: =IF(LEN(B39)=8,LEFT(B39,1),0) -> 0 | B39: G51711441 | C39: CRÉDITOS DE IMPOSTO | D39: 548878.77 | E39: 6592.83 | F39: 0 | G39: 6592.83 | H39: 555471.6
A40: =IF(LEN(B40)=8,LEFT(B40,1),0) -> 0 | B40: G517114411 | C40: IMPOSTO DE RENDA A C | D40: 548878.77 | E40: 6592.83 | F40: 0 | G40: 6592.83 | H40: 555471.6
A41: =IF(LEN(B41)=8,LEFT(B41,1),0) -> 1 | B41: 11641001 | C41: IRPJ A COMPENSAR CP | D41: 105179.91 | E41: 946.29 | F41: 0 | G41: 946.29 | H41: 106126.2
A42: =IF(LEN(B42)=8,LEFT(B42,1),0) -> 1 | B42: 11641008 | C42: IR RETIDO S/APL FIN | D42: 443698.86 | E42: 5646.54 | F42: 0 | G42: 5646.54 | H42: 449345.4
A43: =IF(LEN(B43)=8,LEFT(B43,1),0) -> 0 | B43: G51711442 | C43: CRÉDITOS DE CONTRIBU | D43: 835094.52 | E43: 7584.67 | F43: 0 | G43: 7584.67 | H43: 842679.19
A44: =IF(LEN(B44)=8,LEFT(B44,1),0) -> 0 | B44: G517114421 | C44: CONTRIBUIÇÃO SOCIAL | D44: 768701.95 | E44: 6665.46 | F44: 0 | G44: 6665.46 | H44: 775367.41
A45: =IF(LEN(B45)=8,LEFT(B45,1),0) -> 1 | B45: 11642001 | C45: CSLL A COMPENSAR CP | D45: 768701.95 | E45: 6665.46 | F45: 0 | G45: 6665.46 | H45: 775367.41
A46: =IF(LEN(B46)=8,LEFT(B46,1),0) -> 0 | B46: G517114425 | C46: AJUSTES TEMPORAIS | D46: 66392.57 | E46: 919.21 | F46: 0 | G46: 919.21 | H46: 67311.78
A47: =IF(LEN(B47)=8,LEFT(B47,1),0) -> 1 | B47: 11642005 | C47: CSLL RETIDO A COMP | D47: 66392.57 | E47: 919.21 | F47: 0 | G47: 919.21 | H47: 67311.78
A48: =IF(LEN(B48)=8,LEFT(B48,1),0) -> 0 | B48: G51711445 | C48: CRÉDITOS DE COFINS E | D48: 82818.53 | E48: 3354.98 | F48: 5883.17 | G48: -2528.19 | H48: 80290.34
A49: =IF(LEN(B49)=8,LEFT(B49,1),0) -> 0 | B49: G517114451 | C49: COFINS A COMPENSAR | D49: 68287.53 | E49: 2757.5 | F49: 4854.56 | G49: -2097.06 | H49: 66190.47
A50: =IF(LEN(B50)=8,LEFT(B50,1),0) -> 1 | B50: 11644005 | C50: COFINS RETIDO A COMP | D50: 68287.53 | E50: 2757.5 | F50: 4854.56 | G50: -2097.06 | H50: 66190.47
A51: =IF(LEN(B51)=8,LEFT(B51,1),0) -> 0 | B51: G517114453 | C51: PIS A COMPENSAR | D51: 14531 | E51: 597.48 | F51: 1028.61 | G51: -431.13 | H51: 14099.87
A52: =IF(LEN(B52)=8,LEFT(B52,1),0) -> 1 | B52: 11644004 | C52: PIS RETIDO A COMP | D52: 14531 | E52: 597.48 | F52: 1028.61 | G52: -431.13 | H52: 14099.87
A53: =IF(LEN(B53)=8,LEFT(B53,1),0) -> 0 | B53: G51711448 | C53: OUTROS CRÉDITOS TRIB | D53: 96495.25 | E53: 1359.99 | F53: 0 | G53: 1359.99 | H53: 97855.24
A54: =IF(LEN(B54)=8,LEFT(B54,1),0) -> 1 | B54: 11641009 | C54: IR RETIDO SERV PREST | D54: 96495.25 | E54: 1359.99 | F54: 0 | G54: 1359.99 | H54: 97855.24
A55: =IF(LEN(B55)=8,LEFT(B55,1),0) -> 0 | B55: G51712 | C55: ATIVO NÃO CIRCULANTE | D55: 333333.35 | E55: 528.68 | F55: 11639.79 | G55: -11111.11 | H55: 322222.24
A56: =IF(LEN(B56)=8,LEFT(B56,1),0) -> 0 | B56: G517121 | C56: REALIZÁVEL A LONGO P | D56: 333333.35 | E56: 528.68 | F56: 11639.79 | G56: -11111.11 | H56: 322222.24
A57: =IF(LEN(B57)=8,LEFT(B57,1),0) -> G | B57: G5171213 | C57: TÍTULOS E CRÉDITOS A | D57: 333333.35 | E57: 528.68 | F57: 11639.79 | G57: -11111.11 | H57: 322222.24
A58: =IF(LEN(B58)=8,LEFT(B58,1),0) -> 0 | B58: G51712131 | C58: CRÉDITOS A RECEBER | D58: 333333.35 | E58: 528.68 | F58: 11639.79 | G58: -11111.11 | H58: 322222.24
A59: =IF(LEN(B59)=8,LEFT(B59,1),0) -> 0 | B59: G517121311 | C59: CRÉDITOS A RECEBER | D59: 333333.35 | E59: 528.68 | F59: 11639.79 | G59: -11111.11 | H59: 322222.24
A60: =IF(LEN(B60)=8,LEFT(B60,1),0) -> 1 | B60: 12610001 | C60: CRÉDITOS RECEBER-LP | D60: 333333.35 | E60: 528.68 | F60: 11639.79 | G60: -11111.11 | H60: 322222.24
A61: =IF(LEN(B61)=8,LEFT(B61,1),0) -> 0 | B61: G517123 | C61: IMOBILIZADO | D61: 0 | E61: 0 | F61: 0 | G61: 0 | H61: 0
A62: =IF(LEN(B62)=8,LEFT(B62,1),0) -> G | B62: G5171232 | C62: EQUIPAMENTOS | D62: 0 | E62: 0 | F62: 0 | G62: 0 | H62: 0
A63: =IF(LEN(B63)=8,LEFT(B63,1),0) -> 0 | B63: G51712321 | C63: INFORMÁTICA | D63: 16679.39 | E63: 0 | F63: 0 | G63: 0 | H63: 16679.39
A64: =IF(LEN(B64)=8,LEFT(B64,1),0) -> 0 | B64: G517123211 | C64: HARDWARE | D64: 16679.39 | E64: 0 | F64: 0 | G64: 0 | H64: 16679.39
A65: =IF(LEN(B65)=8,LEFT(B65,1),0) -> 1 | B65: 14221001 | C65: EQTOS DE INFORMATICA | D65: 16679.39 | E65: 0 | F65: 0 | G65: 0 | H65: 16679.39
A66: =IF(LEN(B66)=8,LEFT(B66,1),0) -> 0 | B66: G51712322 | C66: TELECOMUNICAÇÕES | D66: 6147 | E66: 0 | F66: 0 | G66: 0 | H66: 6147
A67: =IF(LEN(B67)=8,LEFT(B67,1),0) -> 1 | B67: 14222001 | C67: TELECOMUNICAÇÕES | D67: 6147 | E67: 0 | F67: 0 | G67: 0 | H67: 6147
A68: =IF(LEN(B68)=8,LEFT(B68,1),0) -> 0 | B68: G51712329 | C68: DEPRECIAÇÃO ACUMULAD | D68: -22826.39 | E68: 0 | F68: 0 | G68: 0 | H68: -22826.39
A69: =IF(LEN(B69)=8,LEFT(B69,1),0) -> 0 | B69: G517123291 | C69: DEPRECIAÇÃO ACUMULAD | D69: -22826.39 | E69: 0 | F69: 0 | G69: 0 | H69: -22826.39
A70: =IF(LEN(B70)=8,LEFT(B70,1),0) -> 1 | B70: 14229001 | C70: DEP.ACUM EQTO INFORM | D70: -16679.39 | E70: 0 | F70: 0 | G70: 0 | H70: -16679.39
A71: =IF(LEN(B71)=8,LEFT(B71,1),0) -> 1 | B71: 14229003 | C71: DEP.ACUM TELECOMUNIC | D71: -6147 | E71: 0 | F71: 0 | G71: 0 | H71: -6147
A72: =IF(LEN(B72)=8,LEFT(B72,1),0) -> 0 | B72: G5172 | C72: PASSIVO | D72: -2753631.8 | E72: 52263.8 | F72: 83334.55 | G72: -31070.75 | H72: -2784702.6
A73: =IF(LEN(B73)=8,LEFT(B73,1),0) -> 0 | B73: G51721 | C73: CIRCULANTE | D73: -140415.55 | E73: 52263.8 | F73: 83334.55 | G73: -31070.75 | H73: -171486.3
A74: =IF(LEN(B74)=8,LEFT(B74,1),0) -> 0 | B74: G517211 | C74: CONTAS A PAGAR | D74: -140415.55 | E74: 52263.8 | F74: 83334.55 | G74: -31070.75 | H74: -171486.3
A75: =IF(LEN(B75)=8,LEFT(B75,1),0) -> G | B75: G5172111 | C75: OBRIGAÇÕES A PAGAR | D75: -124822.56 | E75: 33412.02 | F75: 66827.03 | G75: -33415.01 | H75: -158237.57
A76: =IF(LEN(B76)=8,LEFT(B76,1),0) -> 0 | B76: G51721111 | C76: FORNECEDORES | D76: -117195.42 | E76: 26808.15 | F76: 53857.28 | G76: -27049.13 | H76: -144244.55
A77: =IF(LEN(B77)=8,LEFT(B77,1),0) -> 2 | B77: 21111001 | C77: FORN BENS SERVIÇOS | D77: -117195.42 | E77: 25065.68 | F77: 23786.79 | G77: 1278.89 | H77: -115916.53
A78: =IF(LEN(B78)=8,LEFT(B78,1),0) -> 2 | B78: 21111002 | C78: PROV FORNECEDOR CP | D78: 0 | E78: 1742.47 | F78: 30070.49 | G78: -28328.02 | H78: -28328.02
A79: =IF(LEN(B79)=8,LEFT(B79,1),0) -> 0 | B79: G51721119 | C79: OUTRAS OBRIGAÇÕES A | D79: -7627.14 | E79: 6603.87 | F79: 12969.75 | G79: -6365.88 | H79: -13993.02
A80: =IF(LEN(B80)=8,LEFT(B80,1),0) -> 0 | B80: G517211198 | C80: OUTRAS OBRIGAÇÕES | D80: -7627.14 | E80: 6603.87 | F80: 12969.75 | G80: -6365.88 | H80: -13993.02
A81: =IF(LEN(B81)=8,LEFT(B81,1),0) -> 2 | B81: 21111099 | C81: OUTRAS OBRIG.PAGAR | D81: -7627.14 | E81: 6603.87 | F81: 12969.75 | G81: -6365.88 | H81: -13993.02
A82: =IF(LEN(B82)=8,LEFT(B82,1),0) -> G | B82: G5172112 | C82: IMPOSTOS E ENCARGOS | D82: -10055.11 | E82: 13313.9 | F82: 16507.52 | G82: -3193.62 | H82: -13248.73
A83: =IF(LEN(B83)=8,LEFT(B83,1),0) -> 0 | B83: G51721122 | C83: IMPOSTO DE RENDA RET | D83: -275.49 | E83: 275.49 | F83: 0 | G83: 275.49 | H83: 0
A84: =IF(LEN(B84)=8,LEFT(B84,1),0) -> 2 | B84: 21131104 | C84: IRF TERCEIROS RECOL | D84: -275.49 | E84: 275.49 | F84: 0 | G84: 275.49 | H84: 0
A85: =IF(LEN(B85)=8,LEFT(B85,1),0) -> 0 | B85: G51721128 | C85: OUTROS IMPOSTOS E EN | D85: -9779.62 | E85: 13038.41 | F85: 16507.52 | G85: -3469.11 | H85: -13248.73
A86: =IF(LEN(B86)=8,LEFT(B86,1),0) -> 2 | B86: 21131601 | C86: COFINS A RECOLHER | D86: -4854.56 | E86: 4854.56 | F86: 7610.76 | G86: -2756.2 | H86: -7610.76
A87: =IF(LEN(B87)=8,LEFT(B87,1),0) -> 2 | B87: 21131602 | C87: PIS/PASEP A RECOLHER | D87: -1028.61 | E87: 1028.61 | F87: 1619.57 | G87: -590.96 | H87: -1619.57
A88: =IF(LEN(B88)=8,LEFT(B88,1),0) -> 2 | B88: 21131701 | C88: PIS/COFINS/CSLL TERC | D88: -1353.15 | E88: 1353.15 | F88: 0 | G88: 1353.15 | H88: 0
A89: =IF(LEN(B89)=8,LEFT(B89,1),0) -> 2 | B89: 21133102 | C89: ISS S/FATURAMENTO | D89: -2543.3 | E89: 5802.09 | F89: 7277.19 | G89: -1475.1 | H89: -4018.4
A90: =IF(LEN(B90)=8,LEFT(B90,1),0) -> G | B90: G5172116 | C90: IMPOSTOS E CONTRIBUI | D90: -5537.88 | E90: 5537.88 | F90: 0 | G90: 5537.88 | H90: 0
A91: =IF(LEN(B91)=8,LEFT(B91,1),0) -> 0 | B91: G51721161 | C91: IMPOSTO DE RENDA | D91: -3542.56 | E91: 3542.56 | F91: 0 | G91: 3542.56 | H91: 0
A92: =IF(LEN(B92)=8,LEFT(B92,1),0) -> 0 | B92: G517211611 | C92: IMPOSTO DE RENDA | D92: -15084.52 | E92: 0 | F92: 0 | G92: 0 | H92: -15084.52
A93: =IF(LEN(B93)=8,LEFT(B93,1),0) -> 2 | B93: 21131101 | C93: PROVISÃO PARA IRPJ | D93: -15084.52 | E93: 0 | F93: 0 | G93: 0 | H93: -15084.52
A94: =IF(LEN(B94)=8,LEFT(B94,1),0) -> 0 | B94: G517211612 | C94: (-) ANTECIPAÇÃO DE I | D94: 11541.96 | E94: 3542.56 | F94: 0 | G94: 3542.56 | H94: 15084.52
A95: =IF(LEN(B95)=8,LEFT(B95,1),0) -> 2 | B95: 21131102 | C95: (-) ANTECIPACAO IRPJ | D95: 11541.96 | E95: 3542.56 | F95: 0 | G95: 3542.56 | H95: 15084.52
A96: =IF(LEN(B96)=8,LEFT(B96,1),0) -> 0 | B96: G51721162 | C96: CONTRIBUIÇÃO SOCIAL | D96: -1995.32 | E96: 1995.32 | F96: 0 | G96: 1995.32 | H96: 0
A97: =IF(LEN(B97)=8,LEFT(B97,1),0) -> 0 | B97: G517211621 | C97: CONTRIBUIÇÃO SOCIAL | D97: -8310.43 | E97: 0 | F97: 0 | G97: 0 | H97: -8310.43
A98: =IF(LEN(B98)=8,LEFT(B98,1),0) -> 2 | B98: 21131201 | C98: PROVISÃO PARA CSLL | D98: -8310.43 | E98: 0 | F98: 0 | G98: 0 | H98: -8310.43
A99: =IF(LEN(B99)=8,LEFT(B99,1),0) -> 0 | B99: G517211622 | C99: (-) ANTECIPAÇÃO DE C | D99: 6315.11 | E99: 1995.32 | F99: 0 | G99: 1995.32 | H99: 8310.43
A100: =IF(LEN(B100)=8,LEFT(B100,1),0) -> 2 | B100: 21131202 | C100: (-) ANTECIPAÇÃO CSLL | D100: 6315.11 | E100: 1995.32 | F100: 0 | G100: 1995.32 | H100: 8310.43
...

Sheet Bal 042026
B1: Table
C2: Exercício/período | D2: 004.2026 | E2: 004.2026 | F2: 004.2026 | G2: 004.2026 | H2: 004.2026
B3: Conta do Razão | D3: Saldo Anterior | E3: Débitos | F3: Créditos | G3: Movimento | H3: Saldo Acumulado
A4: =IF(LEN(B4)=8,LEFT(B4,1),0) -> 0 | B4: G517 | C4: PLANO DE CONTAS CONS | D4: 0 | E4: 750863.5 | F4: 750863.5 | G4: 0 | H4: 0
A5: =IF(LEN(B5)=8,LEFT(B5,1),0) -> 0 | B5: G5171 | C5: ATIVO | D5: 2803994 | E5: 575790.38 | F5: 557209.35 | G5: 18581.03 | H5: 2822575
A6: =IF(LEN(B6)=8,LEFT(B6,1),0) -> 0 | B6: G51711 | C6: CIRCULANTE | D6: 2459549.5 | E6: 575261.7 | F6: 545569.56 | G6: 29692.14 | H6: 2489241.6
A7: =IF(LEN(B7)=8,LEFT(B7,1),0) -> 0 | B7: G517111 | C7: DISPONÍVEL | D7: 110572.37 | E7: 493181.4 | F7: 484229.02 | G7: 8952.38 | H7: 119524.75
A8: =IF(LEN(B8)=8,LEFT(B8,1),0) -> G | B8: G5171113 | C8: BANCOS CONTA DEPÓSIT | D8: 110572.37 | E8: 493181.4 | F8: 484229.02 | G8: 8952.38 | H8: 119524.75
A9: =IF(LEN(B9)=8,LEFT(B9,1),0) -> 0 | B9: G51711131 | C9: BANCOS CONTA DEPÓSIT | D9: 110572.37 | E9: 493181.4 | F9: 484229.02 | G9: 8952.38 | H9: 119524.75
A10: =IF(LEN(B10)=8,LEFT(B10,1),0) -> 1 | B10: 11131050 | C10: BCO SANTANDER | D10: 12296.21 | E10: 91639.79 | F10: 46807.81 | G10: 44831.98 | H10: 57128.19
A11: =IF(LEN(B11)=8,LEFT(B11,1),0) -> 1 | B11: 11131090 | C11: BANCO SANTANDER | D11: 98531.02 | E11: 44506.3 | F11: 80231.89 | G11: -35725.59 | H11: 62805.43
A12: =IF(LEN(B12)=8,LEFT(B12,1),0) -> 1 | B12: 11131091 | C12: BANCO SANTANDER | D12: 0 | E12: 1 | F12: 0 | G12: 1 | H12: 1
A13: =IF(LEN(B13)=8,LEFT(B13,1),0) -> 1 | B13: 11132050 | C13: BCO SANTANDER | D13: 0 | E13: 91639.79 | F13: 91639.79 | G13: 0 | H13: 0
A14: =IF(LEN(B14)=8,LEFT(B14,1),0) -> 1 | B14: 11132090 | C14: BANCO SANTANDER | D14: -255.86 | E14: 91966.9 | F14: 92120.91 | G14: -154.01 | H14: -409.87
A15: =IF(LEN(B15)=8,LEFT(B15,1),0) -> 1 | B15: 11132091 | C15: BANCO SANTANDER | D15: 0 | E15: 1 | F15: 1 | G15: 0 | H15: 0
A16: =IF(LEN(B16)=8,LEFT(B16,1),0) -> 1 | B16: 11133050 | C16: BCO SANTANDER SAIDA | D16: 1 | E16: 93426.62 | F16: 93427.62 | G16: -1 | H16: 0
A17: =IF(LEN(B17)=8,LEFT(B17,1),0) -> 1 | B17: 11133090 | C17: BANCO SANTANDER | D17: 0 | E17: 80000 | F17: 80000 | G17: 0 | H17: 0
A18: =IF(LEN(B18)=8,LEFT(B18,1),0) -> 0 | B18: G517112 | C18: APLICAÇÕES | D18: 608330.43 | E18: 6578.34 | F18: 0 | G18: 6578.34 | H18: 614908.77
A19: =IF(LEN(B19)=8,LEFT(B19,1),0) -> G | B19: G5171126 | C19: QUOTAS DE FUNDOS DE | D19: 608330.43 | E19: 6578.34 | F19: 0 | G19: 6578.34 | H19: 614908.77
A20: =IF(LEN(B20)=8,LEFT(B20,1),0) -> 0 | B20: G51711261 | C20: VINCULADAS À COBERTU | D20: 608330.43 | E20: 6578.34 | F20: 0 | G20: 6578.34 | H20: 614908.77
A21: =IF(LEN(B21)=8,LEFT(B21,1),0) -> 0 | B21: G517112612 | C21: QUOTAS DE OUTROS FUN | D21: 608330.43 | E21: 6578.34 | F21: 0 | G21: 6578.34 | H21: 614908.77
A22: =IF(LEN(B22)=8,LEFT(B22,1),0) -> 0 | B22: G5171126121 | C22: VALOR ORIGINAL | D22: 608330.43 | E22: 6578.34 | F22: 0 | G22: 6578.34 | H22: 614908.77
A23: =IF(LEN(B23)=8,LEFT(B23,1),0) -> 1 | B23: 11240001 | C23: FD ÑEX CUV VC CP DPV | D23: 608330.43 | E23: 6578.34 | F23: 0 | G23: 6578.34 | H23: 614908.77
A24: =IF(LEN(B24)=8,LEFT(B24,1),0) -> 0 | B24: G517113 | C24: CRÉDITOS DAS OPERAÇÕ | D24: 25093.5 | E24: 61659.73 | F24: 53634.73 | G24: 8025 | H24: 33118.5
A25: =IF(LEN(B25)=8,LEFT(B25,1),0) -> G | B25: G5171131 | C25: PRÊMIOS A RECEBER | D25: 25093.5 | E25: 61409.73 | F25: 53384.73 | G25: 8025 | H25: 33118.5
A26: =IF(LEN(B26)=8,LEFT(B26,1),0) -> 0 | B26: G51711311 | C26: DIRETO | D26: 25093.5 | E26: 61409.73 | F26: 53384.73 | G26: 8025 | H26: 33118.5
A27: =IF(LEN(B27)=8,LEFT(B27,1),0) -> 0 | B27: G517113111 | C27: PRÊMIOS - RISCOS VIG | D27: 25093.5 | E27: 61409.73 | F27: 53384.73 | G27: 8025 | H27: 33118.5
A28: =IF(LEN(B28)=8,LEFT(B28,1),0) -> 1 | B28: 11311011 | C28: SOMPO SEG REC RECEIT | D28: 0 | E28: 2559.73 | F28: 2559.73 | G28: 0 | H28: 0
A29: =IF(LEN(B29)=8,LEFT(B29,1),0) -> 1 | B29: 11311094 | C29: Clientes SompoRisk | D29: 25093.5 | E29: 58850 | F29: 50825 | G29: 8025 | H29: 33118.5
A30: =IF(LEN(B30)=8,LEFT(B30,1),0) -> G | B30: G5171138 | C30: OUTROS CRÉDITOS OPER | D30: 0 | E30: 250 | F30: 250 | G30: 0 | H30: 0
A31: =IF(LEN(B31)=8,LEFT(B31,1),0) -> 0 | B31: G51711388 | C31: OUTROS CRÉDITOS | D31: 0 | E31: 250 | F31: 250 | G31: 0 | H31: 0
A32: =IF(LEN(B32)=8,LEFT(B32,1),0) -> 1 | B32: 11391004 | C32: SALVADO VEND RECEBER | D32: 0 | E32: 250 | F32: 250 | G32: 0 | H32: 0
A33: =IF(LEN(B33)=8,LEFT(B33,1),0) -> 0 | B33: G517114 | C33: TÍTULOS E CRÉDITOS A | D33: 1715553.2 | E33: 13842.23 | F33: 7705.81 | G33: 6136.42 | H33: 1721689.6
A34: =IF(LEN(B34)=8,LEFT(B34,1),0) -> G | B34: G5171141 | C34: CRÉDITOS A RECEBER | D34: 155842.81 | E34: 2559.73 | F34: 0 | G34: 2559.73 | H34: 158402.54
A35: =IF(LEN(B35)=8,LEFT(B35,1),0) -> 0 | B35: G51711418 | C35: OUTROS CRÉDITOS A RE | D35: 155842.81 | E35: 2559.73 | F35: 0 | G35: 2559.73 | H35: 158402.54
A36: =IF(LEN(B36)=8,LEFT(B36,1),0) -> 1 | B36: 11610099 | C36: OUTROS CRÉD.RECEBER | D36: 155842.81 | E36: 2559.73 | F36: 0 | G36: 2559.73 | H36: 158402.54
A37: =IF(LEN(B37)=8,LEFT(B37,1),0) -> G | B37: G5171144 | C37: CRÉDITOS TRIBUTÁRIOS | D37: 1559710.4 | E37: 11282.5 | F37: 7705.81 | G37: 3576.69 | H37: 1563287.1
A38: =IF(LEN(B38)=8,LEFT(B38,1),0) -> 0 | B38: G51711441 | C38: CRÉDITOS DE IMPOSTO | D38: 548082.65 | E38: 796.12 | F38: 0 | G38: 796.12 | H38: 548878.77
A39: =IF(LEN(B39)=8,LEFT(B39,1),0) -> 0 | B39: G517114411 | C39: IMPOSTO DE RENDA A C | D39: 548082.65 | E39: 796.12 | F39: 0 | G39: 796.12 | H39: 548878.77
A40: =IF(LEN(B40)=8,LEFT(B40,1),0) -> 1 | B40: 11641001 | C40: IRPJ A COMPENSAR CP | D40: 104383.79 | E40: 796.12 | F40: 0 | G40: 796.12 | H40: 105179.91
A41: =IF(LEN(B41)=8,LEFT(B41,1),0) -> 1 | B41: 11641008 | C41: IR RETIDO S/APL FIN | D41: 443698.86 | E41: 0 | F41: 0 | G41: 0 | H41: 443698.86
A42: =IF(LEN(B42)=8,LEFT(B42,1),0) -> 0 | B42: G51711442 | C42: CRÉDITOS DE CONTRIBU | D42: 830931.52 | E42: 4196.12 | F42: 33.12 | G42: 4163 | H42: 835094.52
A43: =IF(LEN(B43)=8,LEFT(B43,1),0) -> 0 | B43: G517114421 | C43: CONTRIBUIÇÃO SOCIAL | D43: 765002.53 | E43: 3699.42 | F43: 0 | G43: 3699.42 | H43: 768701.95
A44: =IF(LEN(B44)=8,LEFT(B44,1),0) -> 1 | B44: 11642001 | C44: CSLL A COMPENSAR CP | D44: 765002.53 | E44: 3699.42 | F44: 0 | G44: 3699.42 | H44: 768701.95
A45: =IF(LEN(B45)=8,LEFT(B45,1),0) -> 0 | B45: G517114425 | C45: AJUSTES TEMPORAIS | D45: 65928.99 | E45: 496.7 | F45: 33.12 | G45: 463.58 | H45: 66392.57
A46: =IF(LEN(B46)=8,LEFT(B46,1),0) -> 1 | B46: 11642005 | C46: CSLL RETIDO A COMP | D46: 65928.99 | E46: 496.7 | F46: 33.12 | G46: 463.58 | H46: 66392.57
A47: =IF(LEN(B47)=8,LEFT(B47,1),0) -> 0 | B47: G51711445 | C47: CRÉDITOS DE COFINS E | D47: 84877.55 | E47: 5563.99 | F47: 7623.01 | G47: -2059.02 | H47: 82818.53
A48: =IF(LEN(B48)=8,LEFT(B48,1),0) -> 0 | B48: G517114451 | C48: COFINS A COMPENSAR | D48: 69978.79 | E48: 4572.02 | F48: 6263.28 | G48: -1691.26 | H48: 68287.53
A49: =IF(LEN(B49)=8,LEFT(B49,1),0) -> 1 | B49: 11644005 | C49: COFINS RETIDO A COMP | D49: 69978.79 | E49: 4572.02 | F49: 6263.28 | G49: -1691.26 | H49: 68287.53
A50: =IF(LEN(B50)=8,LEFT(B50,1),0) -> 0 | B50: G517114453 | C50: PIS A COMPENSAR | D50: 14898.76 | E50: 991.97 | F50: 1359.73 | G50: -367.76 | H50: 14531
A51: =IF(LEN(B51)=8,LEFT(B51,1),0) -> 1 | B51: 11644004 | C51: PIS RETIDO A COMP | D51: 14898.76 | E51: 991.97 | F51: 1359.73 | G51: -367.76 | H51: 14531
A52: =IF(LEN(B52)=8,LEFT(B52,1),0) -> 0 | B52: G51711448 | C52: OUTROS CRÉDITOS TRIB | D52: 95818.66 | E52: 726.27 | F52: 49.68 | G52: 676.59 | H52: 96495.25
A53: =IF(LEN(B53)=8,LEFT(B53,1),0) -> 1 | B53: 11641009 | C53: IR RETIDO SERV PREST | D53: 95818.66 | E53: 726.27 | F53: 49.68 | G53: 676.59 | H53: 96495.25
A54: =IF(LEN(B54)=8,LEFT(B54,1),0) -> 0 | B54: G51712 | C54: ATIVO NÃO CIRCULANTE | D54: 344444.46 | E54: 528.68 | F54: 11639.79 | G54: -11111.11 | H54: 333333.35
A55: =IF(LEN(B55)=8,LEFT(B55,1),0) -> 0 | B55: G517121 | C55: REALIZÁVEL A LONGO P | D55: 344444.46 | E55: 528.68 | F55: 11639.79 | G55: -11111.11 | H55: 333333.35
A56: =IF(LEN(B56)=8,LEFT(B56,1),0) -> G | B56: G5171213 | C56: TÍTULOS E CRÉDITOS A | D56: 344444.46 | E56: 528.68 | F56: 11639.79 | G56: -11111.11 | H56: 333333.35
A57: =IF(LEN(B57)=8,LEFT(B57,1),0) -> 0 | B57: G51712131 | C57: CRÉDITOS A RECEBER | D57: 344444.46 | E57: 528.68 | F57: 11639.79 | G57: -11111.11 | H57: 333333.35
A58: =IF(LEN(B58)=8,LEFT(B58,1),0) -> 0 | B58: G517121311 | C58: CRÉDITOS A RECEBER | D58: 344444.46 | E58: 528.68 | F58: 11639.79 | G58: -11111.11 | H58: 333333.35
A59: =IF(LEN(B59)=8,LEFT(B59,1),0) -> 1 | B59: 12610001 | C59: CRÉDITOS RECEBER-LP | D59: 344444.46 | E59: 528.68 | F59: 11639.79 | G59: -11111.11 | H59: 333333.35
A60: =IF(LEN(B60)=8,LEFT(B60,1),0) -> 0 | B60: G517123 | C60: IMOBILIZADO | D60: 0 | E60: 0 | F60: 0 | G60: 0 | H60: 0
A61: =IF(LEN(B61)=8,LEFT(B61,1),0) -> G | B61: G5171232 | C61: EQUIPAMENTOS | D61: 0 | E61: 0 | F61: 0 | G61: 0 | H61: 0
A62: =IF(LEN(B62)=8,LEFT(B62,1),0) -> 0 | B62: G51712321 | C62: INFORMÁTICA | D62: 16679.39 | E62: 0 | F62: 0 | G62: 0 | H62: 16679.39
A63: =IF(LEN(B63)=8,LEFT(B63,1),0) -> 0 | B63: G517123211 | C63: HARDWARE | D63: 16679.39 | E63: 0 | F63: 0 | G63: 0 | H63: 16679.39
A64: =IF(LEN(B64)=8,LEFT(B64,1),0) -> 1 | B64: 14221001 | C64: EQTOS DE INFORMATICA | D64: 16679.39 | E64: 0 | F64: 0 | G64: 0 | H64: 16679.39
A65: =IF(LEN(B65)=8,LEFT(B65,1),0) -> 0 | B65: G51712322 | C65: TELECOMUNICAÇÕES | D65: 6147 | E65: 0 | F65: 0 | G65: 0 | H65: 6147
A66: =IF(LEN(B66)=8,LEFT(B66,1),0) -> 1 | B66: 14222001 | C66: TELECOMUNICAÇÕES | D66: 6147 | E66: 0 | F66: 0 | G66: 0 | H66: 6147
A67: =IF(LEN(B67)=8,LEFT(B67,1),0) -> 0 | B67: G51712329 | C67: DEPRECIAÇÃO ACUMULAD | D67: -22826.39 | E67: 0 | F67: 0 | G67: 0 | H67: -22826.39
A68: =IF(LEN(B68)=8,LEFT(B68,1),0) -> 0 | B68: G517123291 | C68: DEPRECIAÇÃO ACUMULAD | D68: -22826.39 | E68: 0 | F68: 0 | G68: 0 | H68: -22826.39
A69: =IF(LEN(B69)=8,LEFT(B69,1),0) -> 1 | B69: 14229001 | C69: DEP.ACUM EQTO INFORM | D69: -16679.39 | E69: 0 | F69: 0 | G69: 0 | H69: -16679.39
A70: =IF(LEN(B70)=8,LEFT(B70,1),0) -> 1 | B70: 14229003 | C70: DEP.ACUM TELECOMUNIC | D70: -6147 | E70: 0 | F70: 0 | G70: 0 | H70: -6147
A71: =IF(LEN(B71)=8,LEFT(B71,1),0) -> 0 | B71: G5172 | C71: PASSIVO | D71: -2751683.2 | E71: 98267.23 | F71: 100215.9 | G71: -1948.67 | H71: -2753631.8
A72: =IF(LEN(B72)=8,LEFT(B72,1),0) -> 0 | B72: G51721 | C72: CIRCULANTE | D72: -138466.88 | E72: 98267.23 | F72: 100215.9 | G72: -1948.67 | H72: -140415.55
A73: =IF(LEN(B73)=8,LEFT(B73,1),0) -> 0 | B73: G517211 | C73: CONTAS A PAGAR | D73: -138466.88 | E73: 98267.23 | F73: 100215.9 | G73: -1948.67 | H73: -140415.55
A74: =IF(LEN(B74)=8,LEFT(B74,1),0) -> G | B74: G5172111 | C74: OBRIGAÇÕES A PAGAR | D74: -134329.12 | E74: 82039.53 | F74: 72532.97 | G74: 9506.56 | H74: -124822.56
A75: =IF(LEN(B75)=8,LEFT(B75,1),0) -> 0 | B75: G51721111 | C75: FORNECEDORES | D75: -125807.89 | E75: 74541.57 | F75: 65929.1 | G75: 8612.47 | H75: -117195.42
A76: =IF(LEN(B76)=8,LEFT(B76,1),0) -> 2 | B76: 21111001 | C76: FORN BENS SERVIÇOS | D76: -125807.89 | E76: 48066.46 | F76: 39453.99 | G76: 8612.47 | H76: -117195.42
A77: =IF(LEN(B77)=8,LEFT(B77,1),0) -> 2 | B77: 21111002 | C77: PROV FORNECEDOR CP | D77: 0 | E77: 26475.11 | F77: 26475.11 | G77: 0 | H77: 0
A78: =IF(LEN(B78)=8,LEFT(B78,1),0) -> 0 | B78: G51721119 | C78: OUTRAS OBRIGAÇÕES A | D78: -8521.23 | E78: 7497.96 | F78: 6603.87 | G78: 894.09 | H78: -7627.14
A79: =IF(LEN(B79)=8,LEFT(B79,1),0) -> 0 | B79: G517211198 | C79: OUTRAS OBRIGAÇÕES | D79: -8521.23 | E79: 7497.96 | F79: 6603.87 | G79: 894.09 | H79: -7627.14
A80: =IF(LEN(B80)=8,LEFT(B80,1),0) -> 2 | B80: 21111099 | C80: OUTRAS OBRIG.PAGAR | D80: -8521.23 | E80: 7497.96 | F80: 6603.87 | G80: 894.09 | H80: -7627.14
A81: =IF(LEN(B81)=8,LEFT(B81,1),0) -> G | B81: G5172112 | C81: IMPOSTOS E ENCARGOS | D81: 332.27 | E81: 11757.67 | F81: 22145.05 | G81: -10387.38 | H81: -10055.11
A82: =IF(LEN(B82)=8,LEFT(B82,1),0) -> 0 | B82: G51721122 | C82: IMPOSTO DE RENDA RET | D82: -814.21 | E82: 814.21 | F82: 275.49 | G82: 538.72 | H82: -275.49
A83: =IF(LEN(B83)=8,LEFT(B83,1),0) -> 2 | B83: 21131104 | C83: IRF TERCEIROS RECOL | D83: -814.21 | E83: 814.21 | F83: 275.49 | G83: 538.72 | H83: -275.49
A84: =IF(LEN(B84)=8,LEFT(B84,1),0) -> 0 | B84: G51721128 | C84: OUTROS IMPOSTOS E EN | D84: 1146.48 | E84: 10943.46 | F84: 21869.56 | G84: -10926.1 | H84: -9779.62
A85: =IF(LEN(B85)=8,LEFT(B85,1),0) -> 2 | B85: 21131601 | C85: COFINS A RECOLHER | D85: 3556.37 | E85: 6163.92 | F85: 14574.85 | G85: -8410.93 | H85: -4854.56
A86: =IF(LEN(B86)=8,LEFT(B86,1),0) -> 2 | B86: 21131602 | C86: PIS/PASEP A RECOLHER | D86: 736.26 | E86: 1338.2 | F86: 3103.07 | G86: -1764.87 | H86: -1028.61
A87: =IF(LEN(B87)=8,LEFT(B87,1),0) -> 2 | B87: 21131701 | C87: PIS/COFINS/CSLL TERC | D87: -1533.57 | E87: 1533.57 | F87: 1353.15 | G87: 180.42 | H87: -1353.15
A88: =IF(LEN(B88)=8,LEFT(B88,1),0) -> 2 | B88: 21133102 | C88: ISS S/FATURAMENTO | D88: -1612.58 | E88: 1907.77 | F88: 2838.49 | G88: -930.72 | H88: -2543.3
A89: =IF(LEN(B89)=8,LEFT(B89,1),0) -> G | B89: G5172116 | C89: IMPOSTOS E CONTRIBUI | D89: -4470.03 | E89: 4470.03 | F89: 5537.88 | G89: -1067.85 | H89: -5537.88
A90: =IF(LEN(B90)=8,LEFT(B90,1),0) -> 0 | B90: G51721161 | C90: IMPOSTO DE RENDA | D90: -2227.96 | E90: 2227.96 | F90: 3542.56 | G90: -1314.6 | H90: -3542.56
A91: =IF(LEN(B91)=8,LEFT(B91,1),0) -> 0 | B91: G517211611 | C91: IMPOSTO DE RENDA | D91: -11541.96 | E91: 0 | F91: 3542.56 | G91: -3542.56 | H91: -15084.52
A92: =IF(LEN(B92)=8,LEFT(B92,1),0) -> 2 | B92: 21131101 | C92: PROVISÃO PARA IRPJ | D92: -11541.96 | E92: 0 | F92: 3542.56 | G92: -3542.56 | H92: -15084.52
A93: =IF(LEN(B93)=8,LEFT(B93,1),0) -> 0 | B93: G517211612 | C93: (-) ANTECIPAÇÃO DE I | D93: 9314 | E93: 2227.96 | F93: 0 | G93: 2227.96 | H93: 11541.96
A94: =IF(LEN(B94)=8,LEFT(B94,1),0) -> 2 | B94: 21131102 | C94: (-) ANTECIPACAO IRPJ | D94: 9314 | E94: 2227.96 | F94: 0 | G94: 2227.96 | H94: 11541.96
A95: =IF(LEN(B95)=8,LEFT(B95,1),0) -> 0 | B95: G51721162 | C95: CONTRIBUIÇÃO SOCIAL | D95: -2242.07 | E95: 2242.07 | F95: 1995.32 | G95: 246.75 | H95: -1995.32
A96: =IF(LEN(B96)=8,LEFT(B96,1),0) -> 0 | B96: G517211621 | C96: CONTRIBUIÇÃO SOCIAL | D96: -6315.11 | E96: 0 | F96: 1995.32 | G96: -1995.32 | H96: -8310.43
A97: =IF(LEN(B97)=8,LEFT(B97,1),0) -> 2 | B97: 21131201 | C97: PROVISÃO PARA CSLL | D97: -6315.11 | E97: 0 | F97: 1995.32 | G97: -1995.32 | H97: -8310.43
A98: =IF(LEN(B98)=8,LEFT(B98,1),0) -> 0 | B98: G517211622 | C98: (-) ANTECIPAÇÃO DE C | D98: 4073.04 | E98: 2242.07 | F98: 0 | G98: 2242.07 | H98: 6315.11
A99: =IF(LEN(B99)=8,LEFT(B99,1),0) -> 2 | B99: 21131202 | C99: (-) ANTECIPAÇÃO CSLL | D99: 4073.04 | E99: 2242.07 | F99: 0 | G99: 2242.07 | H99: 6315.11
A100: =IF(LEN(B100)=8,LEFT(B100,1),0) -> 0 | B100: G51724 | C100: PATRIMÔNIO LÍQUIDO O | D100: -2613216.3 | E100: 0 | F100: 0 | G100: 0 | H100: -2613216.3
...

Sheet Bal 032026
B1: Table
C2: Exercício/período | D2: 003.2026 | E2: 003.2026 | F2: 003.2026 | G2: 003.2026 | H2: 003.2026
B3: Conta do Razão | D3: Saldo Anterior | E3: Débitos | F3: Créditos | G3: Movimento | H3: Saldo Acumulado
A4: =IF(LEN(B4)=8,LEFT(B4,1),0) -> 0 | B4: C596 | C4: PLANO DE CONTAS SUSE | D4: -636846.24 | E4: 490521.67 | F4: 462323.14 | G4: 28198.53 | H4: -608647.71
A5: =IF(LEN(B5)=8,LEFT(B5,1),0) -> 0 | B5: C5961 | C5: ATIVO | D5: 2082079.4 | E5: 225066.96 | F5: 218569.97 | G5: 6496.99 | H5: 2088576.4
A6: =IF(LEN(B6)=8,LEFT(B6,1),0) -> 0 | B6: C59611 | C6: CIRCULANTE | D6: 1726523.8 | E6: 224538.28 | F6: 206930.18 | G6: 17608.1 | H6: 1744131.9
A7: =IF(LEN(B7)=8,LEFT(B7,1),0) -> 0 | B7: C596111 | C7: DISPONÍVEL | D7: 93261.73 | E7: 203797.86 | F7: 186487.22 | G7: 17310.64 | H7: 110572.37
A8: =IF(LEN(B8)=8,LEFT(B8,1),0) -> C | B8: C5961113 | C8: BANCOS CONTA DEPÓSIT | D8: 93261.73 | E8: 203797.86 | F8: 186487.22 | G8: 17310.64 | H8: 110572.37
A9: =IF(LEN(B9)=8,LEFT(B9,1),0) -> 0 | B9: C59611131 | C9: BANCOS CONTA DEPÓSIT | D9: 93261.73 | E9: 203797.86 | F9: 186487.22 | G9: 17310.64 | H9: 110572.37
A10: =IF(LEN(B10)=8,LEFT(B10,1),0) -> 1 | B10: 11131050 | C10: BCO SANTANDER | D10: 20105.37 | E10: 31639.79 | F10: 39448.95 | G10: -7809.16 | H10: 12296.21
A11: =IF(LEN(B11)=8,LEFT(B11,1),0) -> 1 | B11: 11131090 | C11: BANCO SANTANDER | D11: 73155.36 | E11: 25574.79 | F11: 199.13 | G11: 25375.66 | H11: 98531.02
A12: =IF(LEN(B12)=8,LEFT(B12,1),0) -> 1 | B12: 11132050 | C12: BCO SANTANDER | D12: 0 | E12: 31639.79 | F12: 31639.79 | G12: 0 | H12: 0
A13: =IF(LEN(B13)=8,LEFT(B13,1),0) -> 1 | B13: 11132090 | C13: BANCO SANTANDER | D13: 0 | E13: 36207.59 | F13: 36463.45 | G13: -255.86 | H13: -255.86
A14: =IF(LEN(B14)=8,LEFT(B14,1),0) -> 1 | B14: 11133050 | C14: BCO SANTANDER SAIDA | D14: 1 | E14: 78735.9 | F14: 78735.9 | G14: 0 | H14: 1
A15: =IF(LEN(B15)=8,LEFT(B15,1),0) -> 0 | B15: C596112 | C15: APLICAÇÕES | D15: 621246.46 | E15: 7276.93 | F15: 20192.96 | G15: -12916.03 | H15: 608330.43
A16: =IF(LEN(B16)=8,LEFT(B16,1),0) -> C | B16: C5961126 | C16: QUOTAS DE FUNDOS DE | D16: 621246.46 | E16: 7276.93 | F16: 20192.96 | G16: -12916.03 | H16: 608330.43
A17: =IF(LEN(B17)=8,LEFT(B17,1),0) -> 0 | B17: C59611261 | C17: VINCULADAS À COBERTU | D17: 621246.46 | E17: 7276.93 | F17: 20192.96 | G17: -12916.03 | H17: 608330.43
A18: =IF(LEN(B18)=8,LEFT(B18,1),0) -> 0 | B18: C596112612 | C18: QUOTAS DE OUTROS FUN | D18: 621246.46 | E18: 7276.93 | F18: 20192.96 | G18: -12916.03 | H18: 608330.43
A19: =IF(LEN(B19)=8,LEFT(B19,1),0) -> 0 | B19: C5961126121 | C19: VALOR ORIGINAL | D19: 621246.46 | E19: 7276.93 | F19: 20192.96 | G19: -12916.03 | H19: 608330.43
A20: =IF(LEN(B20)=8,LEFT(B20,1),0) -> 1 | B20: 11240001 | C20: FD ÑEX CUV VC CP DPV | D20: 621246.46 | E20: 7276.93 | F20: 20192.96 | G20: -12916.03 | H20: 608330.43
A21: =IF(LEN(B21)=8,LEFT(B21,1),0) -> 0 | B21: C596113 | C21: CRÉDITOS DAS OPERAÇÕ | D21: 0 | E21: 250 | F21: 250 | G21: 0 | H21: 0
A22: =IF(LEN(B22)=8,LEFT(B22,1),0) -> C | B22: C5961138 | C22: OUTROS CRÉDITOS OPER | D22: 0 | E22: 250 | F22: 250 | G22: 0 | H22: 0
A23: =IF(LEN(B23)=8,LEFT(B23,1),0) -> 0 | B23: C59611388 | C23: OUTROS CRÉDITOS | D23: 0 | E23: 250 | F23: 250 | G23: 0 | H23: 0
A24: =IF(LEN(B24)=8,LEFT(B24,1),0) -> 1 | B24: 11391004 | C24: SALVADO VEND RECEBER | D24: 0 | E24: 250 | F24: 250 | G24: 0 | H24: 0
A25: =IF(LEN(B25)=8,LEFT(B25,1),0) -> 0 | B25: C596114 | C25: TÍTULOS E CRÉDITOS A | D25: 1012015.6 | E25: 13213.49 | F25: 0 | G25: 13213.49 | H25: 1025229.1
A26: =IF(LEN(B26)=8,LEFT(B26,1),0) -> C | B26: C5961141 | C26: CRÉDITOS A RECEBER | D26: 151237.01 | E26: 4605.8 | F26: 0 | G26: 4605.8 | H26: 155842.81
A27: =IF(LEN(B27)=8,LEFT(B27,1),0) -> 0 | B27: C59611418 | C27: OUTROS CRÉDITOS A RE | D27: 151237.01 | E27: 4605.8 | F27: 0 | G27: 4605.8 | H27: 155842.81
A28: =IF(LEN(B28)=8,LEFT(B28,1),0) -> 1 | B28: 11610099 | C28: OUTROS CRÉD.RECEBER | D28: 151237.01 | E28: 4605.8 | F28: 0 | G28: 4605.8 | H28: 155842.81
A29: =IF(LEN(B29)=8,LEFT(B29,1),0) -> C | B29: C5961144 | C29: CRÉDITOS TRIBUTÁRIOS | D29: 860778.63 | E29: 8607.69 | F29: 0 | G29: 8607.69 | H29: 869386.32
A30: =IF(LEN(B30)=8,LEFT(B30,1),0) -> 0 | B30: C59611441 | C30: CRÉDITOS DE IMPOSTO | D30: 103313.68 | E30: 1070.11 | F30: 0 | G30: 1070.11 | H30: 104383.79
A31: =IF(LEN(B31)=8,LEFT(B31,1),0) -> 0 | B31: C596114411 | C31: IMPOSTO DE RENDA A C | D31: 103313.68 | E31: 1070.11 | F31: 0 | G31: 1070.11 | H31: 104383.79
A32: =IF(LEN(B32)=8,LEFT(B32,1),0) -> 1 | B32: 11641001 | C32: IRPJ A COMPENSAR CP | D32: 103313.68 | E32: 1070.11 | F32: 0 | G32: 1070.11 | H32: 104383.79
A33: =IF(LEN(B33)=8,LEFT(B33,1),0) -> 0 | B33: C59611442 | C33: CRÉDITOS DE CONTRIBU | D33: 757464.95 | E33: 7537.58 | F33: 0 | G33: 7537.58 | H33: 765002.53
A34: =IF(LEN(B34)=8,LEFT(B34,1),0) -> 0 | B34: C596114421 | C34: CONTRIBUIÇÃO SOCIAL | D34: 757464.95 | E34: 7537.58 | F34: 0 | G34: 7537.58 | H34: 765002.53
A35: =IF(LEN(B35)=8,LEFT(B35,1),0) -> 1 | B35: 11642001 | C35: CSLL A COMPENSAR CP | D35: 757464.95 | E35: 7537.58 | F35: 0 | G35: 7537.58 | H35: 765002.53
A36: =IF(LEN(B36)=8,LEFT(B36,1),0) -> 0 | B36: C59612 | C36: ATIVO NÃO CIRCULANTE | D36: 355555.57 | E36: 528.68 | F36: 11639.79 | G36: -11111.11 | H36: 344444.46
A37: =IF(LEN(B37)=8,LEFT(B37,1),0) -> 0 | B37: C596121 | C37: REALIZÁVEL A LONGO P | D37: 355555.57 | E37: 528.68 | F37: 11639.79 | G37: -11111.11 | H37: 344444.46
A38: =IF(LEN(B38)=8,LEFT(B38,1),0) -> C | B38: C5961213 | C38: TÍTULOS E CRÉDITOS A | D38: 355555.57 | E38: 528.68 | F38: 11639.79 | G38: -11111.11 | H38: 344444.46
A39: =IF(LEN(B39)=8,LEFT(B39,1),0) -> 0 | B39: C59612131 | C39: CRÉDITOS A RECEBER | D39: 355555.57 | E39: 528.68 | F39: 11639.79 | G39: -11111.11 | H39: 344444.46
A40: =IF(LEN(B40)=8,LEFT(B40,1),0) -> 0 | B40: C596121311 | C40: CRÉDITOS A RECEBER | D40: 355555.57 | E40: 528.68 | F40: 11639.79 | G40: -11111.11 | H40: 344444.46
A41: =IF(LEN(B41)=8,LEFT(B41,1),0) -> 1 | B41: 12610001 | C41: CRÉDITOS RECEBER-LP | D41: 355555.57 | E41: 528.68 | F41: 11639.79 | G41: -11111.11 | H41: 344444.46
A42: =IF(LEN(B42)=8,LEFT(B42,1),0) -> 0 | B42: C596123 | C42: IMOBILIZADO | D42: 0 | E42: 0 | F42: 0 | G42: 0 | H42: 0
A43: =IF(LEN(B43)=8,LEFT(B43,1),0) -> C | B43: C5961232 | C43: EQUIPAMENTOS | D43: 0 | E43: 0 | F43: 0 | G43: 0 | H43: 0
A44: =IF(LEN(B44)=8,LEFT(B44,1),0) -> 0 | B44: C59612321 | C44: INFORMÁTICA | D44: 16679.39 | E44: 0 | F44: 0 | G44: 0 | H44: 16679.39
A45: =IF(LEN(B45)=8,LEFT(B45,1),0) -> 0 | B45: C596123211 | C45: HARDWARE | D45: 16679.39 | E45: 0 | F45: 0 | G45: 0 | H45: 16679.39
A46: =IF(LEN(B46)=8,LEFT(B46,1),0) -> 1 | B46: 14221001 | C46: EQTOS DE INFORMATICA | D46: 16679.39 | E46: 0 | F46: 0 | G46: 0 | H46: 16679.39
A47: =IF(LEN(B47)=8,LEFT(B47,1),0) -> 0 | B47: C59612322 | C47: TELECOMUNICAÇÕES | D47: 6147 | E47: 0 | F47: 0 | G47: 0 | H47: 6147
A48: =IF(LEN(B48)=8,LEFT(B48,1),0) -> 1 | B48: 14222001 | C48: TELECOMUNICAÇÕES | D48: 6147 | E48: 0 | F48: 0 | G48: 0 | H48: 6147
A49: =IF(LEN(B49)=8,LEFT(B49,1),0) -> 0 | B49: C59612329 | C49: DEPRECIAÇÃO ACUMULAD | D49: -22826.39 | E49: 0 | F49: 0 | G49: 0 | H49: -22826.39
A50: =IF(LEN(B50)=8,LEFT(B50,1),0) -> 0 | B50: C596123291 | C50: DEPRECIAÇÃO ACUMULAD | D50: -22826.39 | E50: 0 | F50: 0 | G50: 0 | H50: -22826.39
A51: =IF(LEN(B51)=8,LEFT(B51,1),0) -> 1 | B51: 14229001 | C51: DEP.ACUM EQTO INFORM | D51: -16679.39 | E51: 0 | F51: 0 | G51: 0 | H51: -16679.39
A52: =IF(LEN(B52)=8,LEFT(B52,1),0) -> 1 | B52: 14229003 | C52: DEP.ACUM TELECOMUNIC | D52: -6147 | E52: 0 | F52: 0 | G52: 0 | H52: -6147
A53: =IF(LEN(B53)=8,LEFT(B53,1),0) -> 0 | B53: C5962 | C53: PASSIVO | D53: -2765185.5 | E53: 149463.29 | F53: 128082.46 | G53: 21380.83 | H53: -2743804.7
A54: =IF(LEN(B54)=8,LEFT(B54,1),0) -> 0 | B54: C59621 | C54: CIRCULANTE | D54: -151969.24 | E54: 149463.29 | F54: 128082.46 | G54: 21380.83 | H54: -130588.41
A55: =IF(LEN(B55)=8,LEFT(B55,1),0) -> 0 | B55: C596211 | C55: CONTAS A PAGAR | D55: -151969.24 | E55: 149463.29 | F55: 128082.46 | G55: 21380.83 | H55: -130588.41
A56: =IF(LEN(B56)=8,LEFT(B56,1),0) -> C | B56: C5962111 | C56: OBRIGAÇÕES A PAGAR | D56: -155762.34 | E56: 144167.84 | F56: 122734.62 | G56: 21433.22 | H56: -134329.12
A57: =IF(LEN(B57)=8,LEFT(B57,1),0) -> 0 | B57: C59621111 | C57: FORNECEDORES | D57: -110619.34 | E57: 101643.87 | F57: 116832.42 | G57: -15188.55 | H57: -125807.89
A58: =IF(LEN(B58)=8,LEFT(B58,1),0) -> 2 | B58: 21111001 | C58: FORN BENS SERVIÇOS | D58: -110619.34 | E58: 40901.52 | F58: 56090.07 | G58: -15188.55 | H58: -125807.89
A59: =IF(LEN(B59)=8,LEFT(B59,1),0) -> 2 | B59: 21111002 | C59: PROV FORNECEDOR CP | D59: 0 | E59: 60742.35 | F59: 60742.35 | G59: 0 | H59: 0
A60: =IF(LEN(B60)=8,LEFT(B60,1),0) -> 0 | B60: C59621119 | C60: OUTRAS OBRIGAÇÕES A | D60: -45143 | E60: 42523.97 | F60: 5902.2 | G60: 36621.77 | H60: -8521.23
A61: =IF(LEN(B61)=8,LEFT(B61,1),0) -> 0 | B61: C596211198 | C61: OUTRAS OBRIGAÇÕES | D61: -45143 | E61: 42523.97 | F61: 5902.2 | G61: 36621.77 | H61: -8521.23
A62: =IF(LEN(B62)=8,LEFT(B62,1),0) -> 2 | B62: 21111099 | C62: OUTRAS OBRIG.PAGAR | D62: -45143 | E62: 42523.97 | F62: 5902.2 | G62: 36621.77 | H62: -8521.23
A63: =IF(LEN(B63)=8,LEFT(B63,1),0) -> C | B63: C5962112 | C63: IMPOSTOS E ENCARGOS | D63: -1002.82 | E63: 5295.45 | F63: 2347.78 | G63: 2947.67 | H63: 1944.85
A64: =IF(LEN(B64)=8,LEFT(B64,1),0) -> 0 | B64: C59621122 | C64: IMPOSTO DE RENDA RET | D64: 0 | E64: 0 | F64: 814.21 | G64: -814.21 | H64: -814.21
A65: =IF(LEN(B65)=8,LEFT(B65,1),0) -> 2 | B65: 21131104 | C65: IRF TERCEIROS RECOL | D65: 0 | E65: 0 | F65: 814.21 | G65: -814.21 | H65: -814.21
A66: =IF(LEN(B66)=8,LEFT(B66,1),0) -> 0 | B66: C59621128 | C66: OUTROS IMPOSTOS E EN | D66: -1002.82 | E66: 5295.45 | F66: 1533.57 | G66: 3761.88 | H66: 2759.06
A67: =IF(LEN(B67)=8,LEFT(B67,1),0) -> 2 | B67: 21131601 | C67: COFINS A RECOLHER | D67: -848.69 | E67: 4405.06 | F67: 0 | G67: 4405.06 | H67: 3556.37
A68: =IF(LEN(B68)=8,LEFT(B68,1),0) -> 2 | B68: 21131602 | C68: PIS/PASEP A RECOLHER | D68: -154.13 | E68: 890.39 | F68: 0 | G68: 890.39 | H68: 736.26
A69: =IF(LEN(B69)=8,LEFT(B69,1),0) -> 2 | B69: 21131701 | C69: PIS/COFINS/CSLL TERC | D69: 0 | E69: 0 | F69: 1533.57 | G69: -1533.57 | H69: -1533.57
A70: =IF(LEN(B70)=8,LEFT(B70,1),0) -> C | B70: C5962116 | C70: IMPOSTOS E CONTRIBUI | D70: 4795.92 | E70: 0 | F70: 3000.06 | G70: -3000.06 | H70: 1795.86
A71: =IF(LEN(B71)=8,LEFT(B71,1),0) -> 0 | B71: C59621161 | C71: IMPOSTO DE RENDA | D71: 3944.55 | E71: 0 | F71: 1147.1 | G71: -1147.1 | H71: 2797.45
A72: =IF(LEN(B72)=8,LEFT(B72,1),0) -> 0 | B72: C596211611 | C72: IMPOSTO DE RENDA | D72: -5369.45 | E72: 0 | F72: 1147.1 | G72: -1147.1 | H72: -6516.55
A73: =IF(LEN(B73)=8,LEFT(B73,1),0) -> 2 | B73: 21131101 | C73: PROVISÃO PARA IRPJ | D73: -5369.45 | E73: 0 | F73: 1147.1 | G73: -1147.1 | H73: -6516.55
A74: =IF(LEN(B74)=8,LEFT(B74,1),0) -> 0 | B74: C596211612 | C74: (-) ANTECIPAÇÃO DE I | D74: 9314 | E74: 0 | F74: 0 | G74: 0 | H74: 9314
A75: =IF(LEN(B75)=8,LEFT(B75,1),0) -> 2 | B75: 21131102 | C75: (-) ANTECIPACAO IRPJ | D75: 9314 | E75: 0 | F75: 0 | G75: 0 | H75: 9314
A76: =IF(LEN(B76)=8,LEFT(B76,1),0) -> 0 | B76: C59621162 | C76: CONTRIBUIÇÃO SOCIAL | D76: 851.37 | E76: 0 | F76: 1852.96 | G76: -1852.96 | H76: -1001.59
A77: =IF(LEN(B77)=8,LEFT(B77,1),0) -> 0 | B77: C596211621 | C77: CONTRIBUIÇÃO SOCIAL | D77: -3221.67 | E77: 0 | F77: 1852.96 | G77: -1852.96 | H77: -5074.63
A78: =IF(LEN(B78)=8,LEFT(B78,1),0) -> 2 | B78: 21131201 | C78: PROVISÃO PARA CSLL | D78: -3221.67 | E78: 0 | F78: 1852.96 | G78: -1852.96 | H78: -5074.63
A79: =IF(LEN(B79)=8,LEFT(B79,1),0) -> 0 | B79: C596211622 | C79: (-) ANTECIPAÇÃO DE C | D79: 4073.04 | E79: 0 | F79: 0 | G79: 0 | H79: 4073.04
A80: =IF(LEN(B80)=8,LEFT(B80,1),0) -> 2 | B80: 21131202 | C80: (-) ANTECIPAÇÃO CSLL | D80: 4073.04 | E80: 0 | F80: 0 | G80: 0 | H80: 4073.04
A81: =IF(LEN(B81)=8,LEFT(B81,1),0) -> 0 | B81: C59624 | C81: PATRIMÔNIO LÍQUIDO O | D81: -2613216.3 | E81: 0 | F81: 0 | G81: 0 | H81: -2613216.3
A82: =IF(LEN(B82)=8,LEFT(B82,1),0) -> 0 | B82: C596241 | C82: PATRIMÔNIO LÍQUIDO | D82: -2613216.3 | E82: 0 | F82: 0 | G82: 0 | H82: -2613216.3
A83: =IF(LEN(B83)=8,LEFT(B83,1),0) -> C | B83: C5962411 | C83: CAPITAL SOCIAL | D83: -1707264 | E83: 0 | F83: 0 | G83: 0 | H83: -1707264
A84: =IF(LEN(B84)=8,LEFT(B84,1),0) -> 0 | B84: C59624111 | C84: CAPITAL NACIONAL | D84: -1707264 | E84: 0 | F84: 0 | G84: 0 | H84: -1707264
A85: =IF(LEN(B85)=8,LEFT(B85,1),0) -> 0 | B85: C596241111 | C85: AÇÕES ORDINÁRIAS | D85: -1707264 | E85: 0 | F85: 0 | G85: 0 | H85: -1707264
A86: =IF(LEN(B86)=8,LEFT(B86,1),0) -> 2 | B86: 24111001 | C86: AÇÕES ORDINÁRIAS | D86: -1707264 | E86: 0 | F86: 0 | G86: 0 | H86: -1707264
A87: =IF(LEN(B87)=8,LEFT(B87,1),0) -> C | B87: C5962418 | C87: LUCROS OU PREJUÍZOS | D87: -905952.29 | E87: 0 | F87: 0 | G87: 0 | H87: -905952.29
A88: =IF(LEN(B88)=8,LEFT(B88,1),0) -> 0 | B88: C59624184 | C88: RESULTADO DO EXERCÍC | D88: -905952.29 | E88: 0 | F88: 0 | G88: 0 | H88: -905952.29
A89: =IF(LEN(B89)=8,LEFT(B89,1),0) -> 2 | B89: 24180004 | C89: RESULTADO EXERCÍCIO | D89: -905952.29 | E89: 0 | F89: 0 | G89: 0 | H89: -905952.29
A90: =IF(LEN(B90)=8,LEFT(B90,1),0) -> 0 | B90: C5963 | C90: RESULTADO | D90: 46259.89 | E90: 115991.42 | F90: 115670.71 | G90: 320.71 | H90: 46580.6
A91: =IF(LEN(B91)=8,LEFT(B91,1),0) -> 0 | B91: C59631 | C91: OPERAÇÕES DE SEGUROS | D91: 20627.22 | E91: 56644.55 | F91: 43417.41 | G91: 13227.14 | H91: 33854.36
A92: =IF(LEN(B92)=8,LEFT(B92,1),0) -> 0 | B92: C596315 | C92: OUTRAS RECEITAS E DE | D92: 20627.22 | E92: 56644.55 | F92: 43417.41 | G92: 13227.14 | H92: 33854.36
A93: =IF(LEN(B93)=8,LEFT(B93,1),0) -> C | B93: C5963151 | C93: OUTRAS RECEITAS OPER | D93: -11896.75 | E93: 0 | F93: 4605.8 | G93: -4605.8 | H93: -16502.55
A94: =IF(LEN(B94)=8,LEFT(B94,1),0) -> 0 | B94: C59631518 | C94: OUTRAS RECEITAS COM | D94: -11896.75 | E94: 0 | F94: 4605.8 | G94: -4605.8 | H94: -16502.55
A95: =IF(LEN(B95)=8,LEFT(B95,1),0) -> 0 | B95: C596315189 | C95: OUTRAS RECEITAS | D95: -11896.75 | E95: 0 | F95: 4605.8 | G95: -4605.8 | H95: -16502.55
A96: =IF(LEN(B96)=8,LEFT(B96,1),0) -> 0 | B96: C5963151898 | C96: OUTRAS | D96: -11896.75 | E96: 0 | F96: 4605.8 | G96: -4605.8 | H96: -16502.55
A97: =IF(LEN(B97)=8,LEFT(B97,1),0) -> 3 | B97: 35199998 | C97: RECEITAS PREST SERV | D97: -11896.75 | E97: 0 | F97: 4605.8 | G97: -4605.8 | H97: -16502.55
A98: =IF(LEN(B98)=8,LEFT(B98,1),0) -> C | B98: C5963152 | C98: OUTRAS DESPESAS OPER | D98: 32523.97 | E98: 56644.55 | F98: 38811.61 | G98: 17832.94 | H98: 50356.91
A99: =IF(LEN(B99)=8,LEFT(B99,1),0) -> 0 | B99: C59631528 | C99: OUTRAS DESPESAS COM | D99: 32523.97 | E99: 56644.55 | F99: 38811.61 | G99: 17832.94 | H99: 50356.91
A100: =IF(LEN(B100)=8,LEFT(B100,1),0) -> 0 | B100: C596315289 | C100: OUTRAS DESPESAS | D100: 32523.97 | E100: 56644.55 | F100: 38811.61 | G100: 17832.94 | H100: 50356.91
...

Sheet Bal 022026
B1: Table
C2: Exercício/período | D2: 002.2026 | E2: 002.2026 | F2: 002.2026 | G2: 002.2026 | H2: 002.2026
B3: Conta do Razão | D3: Saldo Anterior | E3: Débitos | F3: Créditos | G3: Movimento | H3: Saldo Acumulado
A4: =IF(LEN(B4)=8,LEFT(B4,1),0) -> 0 | B4: C596 | C4: PLANO DE CONTAS SUSE | D4: -623154.73 | E4: 283399.58 | F4: 297091.09 | G4: -13691.51 | H4: -636846.24
A5: =IF(LEN(B5)=8,LEFT(B5,1),0) -> 0 | B5: C5961 | C5: ATIVO | D5: 2096637.8 | E5: 163626.94 | F5: 178185.32 | G5: -14558.38 | H5: 2082079.4
A6: =IF(LEN(B6)=8,LEFT(B6,1),0) -> 0 | B6: C59611 | C6: CIRCULANTE | D6: 1729971.1 | E6: 163098.26 | F6: 166545.53 | G6: -3447.27 | H6: 1726523.8
A7: =IF(LEN(B7)=8,LEFT(B7,1),0) -> 0 | B7: C596111 | C7: DISPONÍVEL | D7: 58364.98 | E7: 135355.77 | F7: 100459.02 | G7: 34896.75 | H7: 93261.73
A8: =IF(LEN(B8)=8,LEFT(B8,1),0) -> C | B8: C5961113 | C8: BANCOS CONTA DEPÓSIT | D8: 58364.98 | E8: 135355.77 | F8: 100459.02 | G8: 34896.75 | H8: 93261.73
A9: =IF(LEN(B9)=8,LEFT(B9,1),0) -> 0 | B9: C59611131 | C9: BANCOS CONTA DEPÓSIT | D9: 58364.98 | E9: 135355.77 | F9: 100459.02 | G9: 34896.75 | H9: 93261.73
A10: =IF(LEN(B10)=8,LEFT(B10,1),0) -> 1 | B10: 11131050 | C10: BCO SANTANDER | D10: 24208.48 | E10: 11639.79 | F10: 15742.9 | G10: -4103.11 | H10: 20105.37
A11: =IF(LEN(B11)=8,LEFT(B11,1),0) -> 1 | B11: 11131090 | C11: BANCO SANTANDER | D11: 52576.74 | E11: 20789.05 | F11: 210.43 | G11: 20578.62 | H11: 73155.36
A12: =IF(LEN(B12)=8,LEFT(B12,1),0) -> 1 | B12: 11132050 | C12: BCO SANTANDER | D12: -18421.24 | E12: 30061.03 | F12: 11639.79 | G12: 18421.24 | H12: 0
A13: =IF(LEN(B13)=8,LEFT(B13,1),0) -> 1 | B13: 11132090 | C13: BANCO SANTANDER | D13: 0 | E13: 41578.1 | F13: 41578.1 | G13: 0 | H13: 0
A14: =IF(LEN(B14)=8,LEFT(B14,1),0) -> 1 | B14: 11133050 | C14: BCO SANTANDER SAIDA | D14: 1 | E14: 31287.8 | F14: 31287.8 | G14: 0 | H14: 1
A15: =IF(LEN(B15)=8,LEFT(B15,1),0) -> 0 | B15: C596112 | C15: APLICAÇÕES | D15: 615094.05 | E15: 6152.41 | F15: 0 | G15: 6152.41 | H15: 621246.46
A16: =IF(LEN(B16)=8,LEFT(B16,1),0) -> C | B16: C5961126 | C16: QUOTAS DE FUNDOS DE | D16: 615094.05 | E16: 6152.41 | F16: 0 | G16: 6152.41 | H16: 621246.46
A17: =IF(LEN(B17)=8,LEFT(B17,1),0) -> 0 | B17: C59611261 | C17: VINCULADAS À COBERTU | D17: 615094.05 | E17: 6152.41 | F17: 0 | G17: 6152.41 | H17: 621246.46
A18: =IF(LEN(B18)=8,LEFT(B18,1),0) -> 0 | B18: C596112612 | C18: QUOTAS DE OUTROS FUN | D18: 615094.05 | E18: 6152.41 | F18: 0 | G18: 6152.41 | H18: 621246.46
A19: =IF(LEN(B19)=8,LEFT(B19,1),0) -> 0 | B19: C5961126121 | C19: VALOR ORIGINAL | D19: 615094.05 | E19: 6152.41 | F19: 0 | G19: 6152.41 | H19: 621246.46
A20: =IF(LEN(B20)=8,LEFT(B20,1),0) -> 1 | B20: 11240001 | C20: FD ÑEX CUV VC CP DPV | D20: 615094.05 | E20: 6152.41 | F20: 0 | G20: 6152.41 | H20: 621246.46
A21: =IF(LEN(B21)=8,LEFT(B21,1),0) -> 0 | B21: C596113 | C21: CRÉDITOS DAS OPERAÇÕ | D21: 0 | E21: 69 | F21: 69 | G21: 0 | H21: 0
A22: =IF(LEN(B22)=8,LEFT(B22,1),0) -> C | B22: C5961138 | C22: OUTROS CRÉDITOS OPER | D22: 0 | E22: 69 | F22: 69 | G22: 0 | H22: 0
A23: =IF(LEN(B23)=8,LEFT(B23,1),0) -> 0 | B23: C59611388 | C23: OUTROS CRÉDITOS | D23: 0 | E23: 69 | F23: 69 | G23: 0 | H23: 0
A24: =IF(LEN(B24)=8,LEFT(B24,1),0) -> 1 | B24: 11391004 | C24: SALVADO VEND RECEBER | D24: 0 | E24: 69 | F24: 69 | G24: 0 | H24: 0
A25: =IF(LEN(B25)=8,LEFT(B25,1),0) -> 0 | B25: C596114 | C25: TÍTULOS E CRÉDITOS A | D25: 1056512.1 | E25: 21521.08 | F25: 66017.51 | G25: -44496.43 | H25: 1012015.6
A26: =IF(LEN(B26)=8,LEFT(B26,1),0) -> C | B26: C5961141 | C26: CRÉDITOS A RECEBER | D26: 158968.63 | E26: 11896.75 | F26: 19628.37 | G26: -7731.62 | H26: 151237.01
A27: =IF(LEN(B27)=8,LEFT(B27,1),0) -> 0 | B27: C59611418 | C27: OUTROS CRÉDITOS A RE | D27: 158968.63 | E27: 11896.75 | F27: 19628.37 | G27: -7731.62 | H27: 151237.01
A28: =IF(LEN(B28)=8,LEFT(B28,1),0) -> 1 | B28: 11610099 | C28: OUTROS CRÉD.RECEBER | D28: 158968.63 | E28: 11896.75 | F28: 19628.37 | G28: -7731.62 | H28: 151237.01
A29: =IF(LEN(B29)=8,LEFT(B29,1),0) -> C | B29: C5961144 | C29: CRÉDITOS TRIBUTÁRIOS | D29: 897543.44 | E29: 9624.33 | F29: 46389.14 | G29: -36764.81 | H29: 860778.63
A30: =IF(LEN(B30)=8,LEFT(B30,1),0) -> 0 | B30: C59611441 | C30: CRÉDITOS DE IMPOSTO | D30: 134961.98 | E30: 884.38 | F30: 32532.68 | G30: -31648.3 | H30: 103313.68
A31: =IF(LEN(B31)=8,LEFT(B31,1),0) -> 0 | B31: C596114411 | C31: IMPOSTO DE RENDA A C | D31: 104635.13 | E31: 884.38 | F31: 2205.83 | G31: -1321.45 | H31: 103313.68
A32: =IF(LEN(B32)=8,LEFT(B32,1),0) -> 1 | B32: 11641001 | C32: IRPJ A COMPENSAR CP | D32: 104635.13 | E32: 884.38 | F32: 2205.83 | G32: -1321.45 | H32: 103313.68
A33: =IF(LEN(B33)=8,LEFT(B33,1),0) -> 0 | B33: C596114412 | C33: ANTECIPAÇÃO DE IMPOS | D33: 30326.85 | E33: 0 | F33: 30326.85 | G33: -30326.85 | H33: 0
A34: =IF(LEN(B34)=8,LEFT(B34,1),0) -> 1 | B34: 11641002 | C34: ANTECIPAÇÃO DE IRPJ | D34: 30326.85 | E34: 0 | F34: 30326.85 | G34: -30326.85 | H34: 0
A35: =IF(LEN(B35)=8,LEFT(B35,1),0) -> 0 | B35: C59611442 | C35: CRÉDITOS DE CONTRIBU | D35: 762581.46 | E35: 8739.95 | F35: 13856.46 | G35: -5116.51 | H35: 757464.95
A36: =IF(LEN(B36)=8,LEFT(B36,1),0) -> 0 | B36: C596114421 | C36: CONTRIBUIÇÃO SOCIAL | D36: 748725 | E36: 8739.95 | F36: 0 | G36: 8739.95 | H36: 757464.95
A37: =IF(LEN(B37)=8,LEFT(B37,1),0) -> 1 | B37: 11642001 | C37: CSLL A COMPENSAR CP | D37: 748725 | E37: 8739.95 | F37: 0 | G37: 8739.95 | H37: 757464.95
A38: =IF(LEN(B38)=8,LEFT(B38,1),0) -> 0 | B38: C596114422 | C38: ANTECIPAÇÃO DE CONTR | D38: 13856.46 | E38: 0 | F38: 13856.46 | G38: -13856.46 | H38: 0
A39: =IF(LEN(B39)=8,LEFT(B39,1),0) -> 1 | B39: 11642002 | C39: ANTECIPAÇÃO DE CSLL | D39: 13856.46 | E39: 0 | F39: 13856.46 | G39: -13856.46 | H39: 0
A40: =IF(LEN(B40)=8,LEFT(B40,1),0) -> 0 | B40: C59612 | C40: ATIVO NÃO CIRCULANTE | D40: 366666.68 | E40: 528.68 | F40: 11639.79 | G40: -11111.11 | H40: 355555.57
A41: =IF(LEN(B41)=8,LEFT(B41,1),0) -> 0 | B41: C596121 | C41: REALIZÁVEL A LONGO P | D41: 366666.68 | E41: 528.68 | F41: 11639.79 | G41: -11111.11 | H41: 355555.57
A42: =IF(LEN(B42)=8,LEFT(B42,1),0) -> C | B42: C5961213 | C42: TÍTULOS E CRÉDITOS A | D42: 366666.68 | E42: 528.68 | F42: 11639.79 | G42: -11111.11 | H42: 355555.57
A43: =IF(LEN(B43)=8,LEFT(B43,1),0) -> 0 | B43: C59612131 | C43: CRÉDITOS A RECEBER | D43: 366666.68 | E43: 528.68 | F43: 11639.79 | G43: -11111.11 | H43: 355555.57
A44: =IF(LEN(B44)=8,LEFT(B44,1),0) -> 0 | B44: C596121311 | C44: CRÉDITOS A RECEBER | D44: 366666.68 | E44: 528.68 | F44: 11639.79 | G44: -11111.11 | H44: 355555.57
A45: =IF(LEN(B45)=8,LEFT(B45,1),0) -> 1 | B45: 12610001 | C45: CRÉDITOS RECEBER-LP | D45: 366666.68 | E45: 528.68 | F45: 11639.79 | G45: -11111.11 | H45: 355555.57
A46: =IF(LEN(B46)=8,LEFT(B46,1),0) -> 0 | B46: C596123 | C46: IMOBILIZADO | D46: 0 | E46: 0 | F46: 0 | G46: 0 | H46: 0
A47: =IF(LEN(B47)=8,LEFT(B47,1),0) -> C | B47: C5961232 | C47: EQUIPAMENTOS | D47: 0 | E47: 0 | F47: 0 | G47: 0 | H47: 0
A48: =IF(LEN(B48)=8,LEFT(B48,1),0) -> 0 | B48: C59612321 | C48: INFORMÁTICA | D48: 16679.39 | E48: 0 | F48: 0 | G48: 0 | H48: 16679.39
A49: =IF(LEN(B49)=8,LEFT(B49,1),0) -> 0 | B49: C596123211 | C49: HARDWARE | D49: 16679.39 | E49: 0 | F49: 0 | G49: 0 | H49: 16679.39
A50: =IF(LEN(B50)=8,LEFT(B50,1),0) -> 1 | B50: 14221001 | C50: EQTOS DE INFORMATICA | D50: 16679.39 | E50: 0 | F50: 0 | G50: 0 | H50: 16679.39
A51: =IF(LEN(B51)=8,LEFT(B51,1),0) -> 0 | B51: C59612322 | C51: TELECOMUNICAÇÕES | D51: 6147 | E51: 0 | F51: 0 | G51: 0 | H51: 6147
A52: =IF(LEN(B52)=8,LEFT(B52,1),0) -> 1 | B52: 14222001 | C52: TELECOMUNICAÇÕES | D52: 6147 | E52: 0 | F52: 0 | G52: 0 | H52: 6147
A53: =IF(LEN(B53)=8,LEFT(B53,1),0) -> 0 | B53: C59612329 | C53: DEPRECIAÇÃO ACUMULAD | D53: -22826.39 | E53: 0 | F53: 0 | G53: 0 | H53: -22826.39
A54: =IF(LEN(B54)=8,LEFT(B54,1),0) -> 0 | B54: C596123291 | C54: DEPRECIAÇÃO ACUMULAD | D54: -22826.39 | E54: 0 | F54: 0 | G54: 0 | H54: -22826.39
A55: =IF(LEN(B55)=8,LEFT(B55,1),0) -> 1 | B55: 14229001 | C55: DEP.ACUM EQTO INFORM | D55: -16679.39 | E55: 0 | F55: 0 | G55: 0 | H55: -16679.39
A56: =IF(LEN(B56)=8,LEFT(B56,1),0) -> 1 | B56: 14229003 | C56: DEP.ACUM TELECOMUNIC | D56: -6147 | E56: 0 | F56: 0 | G56: 0 | H56: -6147
A57: =IF(LEN(B57)=8,LEFT(B57,1),0) -> 0 | B57: C5962 | C57: PASSIVO | D57: -2722975.8 | E57: 46448.71 | F57: 88658.4 | G57: -42209.69 | H57: -2765185.5
A58: =IF(LEN(B58)=8,LEFT(B58,1),0) -> 0 | B58: C59621 | C58: CIRCULANTE | D58: -109759.55 | E58: 46448.71 | F58: 88658.4 | G58: -42209.69 | H58: -151969.24
A59: =IF(LEN(B59)=8,LEFT(B59,1),0) -> 0 | B59: C596211 | C59: CONTAS A PAGAR | D59: -109759.55 | E59: 46448.71 | F59: 88658.4 | G59: -42209.69 | H59: -151969.24
A60: =IF(LEN(B60)=8,LEFT(B60,1),0) -> C | B60: C5962111 | C60: OBRIGAÇÕES A PAGAR | D60: -91500.66 | E60: 23393.9 | F60: 87655.58 | G60: -64261.68 | H60: -155762.34
A61: =IF(LEN(B61)=8,LEFT(B61,1),0) -> 0 | B61: C59621111 | C61: FORNECEDORES | D61: -83309.5 | E61: 23393.9 | F61: 50703.74 | G61: -27309.84 | H61: -110619.34
A62: =IF(LEN(B62)=8,LEFT(B62,1),0) -> 2 | B62: 21111001 | C62: FORN BENS SERVIÇOS | D62: -83309.5 | E62: 15643.9 | F62: 42953.74 | G62: -27309.84 | H62: -110619.34
A63: =IF(LEN(B63)=8,LEFT(B63,1),0) -> 2 | B63: 21111002 | C63: PROV FORNECEDOR CP | D63: 0 | E63: 7750 | F63: 7750 | G63: 0 | H63: 0
A64: =IF(LEN(B64)=8,LEFT(B64,1),0) -> 0 | B64: C59621119 | C64: OUTRAS OBRIGAÇÕES A | D64: -8191.16 | E64: 0 | F64: 36951.84 | G64: -36951.84 | H64: -45143
A65: =IF(LEN(B65)=8,LEFT(B65,1),0) -> 0 | B65: C596211198 | C65: OUTRAS OBRIGAÇÕES | D65: -8191.16 | E65: 0 | F65: 36951.84 | G65: -36951.84 | H65: -45143
A66: =IF(LEN(B66)=8,LEFT(B66,1),0) -> 2 | B66: 21111099 | C66: OUTRAS OBRIG.PAGAR | D66: -8191.16 | E66: 0 | F66: 36951.84 | G66: -36951.84 | H66: -45143
A67: =IF(LEN(B67)=8,LEFT(B67,1),0) -> C | B67: C5962112 | C67: IMPOSTOS E ENCARGOS | D67: -4871.85 | E67: 4871.85 | F67: 1002.82 | G67: 3869.03 | H67: -1002.82
A68: =IF(LEN(B68)=8,LEFT(B68,1),0) -> 0 | B68: C59621128 | C68: OUTROS IMPOSTOS E EN | D68: -4871.85 | E68: 4871.85 | F68: 1002.82 | G68: 3869.03 | H68: -1002.82
A69: =IF(LEN(B69)=8,LEFT(B69,1),0) -> 2 | B69: 21131601 | C69: COFINS A RECOLHER | D69: -4029.7 | E69: 4029.7 | F69: 848.69 | G69: 3181.01 | H69: -848.69
A70: =IF(LEN(B70)=8,LEFT(B70,1),0) -> 2 | B70: 21131602 | C70: PIS/PASEP A RECOLHER | D70: -842.15 | E70: 842.15 | F70: 154.13 | G70: 688.02 | H70: -154.13
A71: =IF(LEN(B71)=8,LEFT(B71,1),0) -> C | B71: C5962116 | C71: IMPOSTOS E CONTRIBUI | D71: -13387.04 | E71: 18182.96 | F71: 0 | G71: 18182.96 | H71: 4795.92
A72: =IF(LEN(B72)=8,LEFT(B72,1),0) -> 0 | B72: C59621161 | C72: IMPOSTO DE RENDA | D72: -9314 | E72: 13258.55 | F72: 0 | G72: 13258.55 | H72: 3944.55
A73: =IF(LEN(B73)=8,LEFT(B73,1),0) -> 0 | B73: C596211611 | C73: IMPOSTO DE RENDA | D73: -9314 | E73: 3944.55 | F73: 0 | G73: 3944.55 | H73: -5369.45
A74: =IF(LEN(B74)=8,LEFT(B74,1),0) -> 2 | B74: 21131101 | C74: PROVISÃO PARA IRPJ | D74: -9314 | E74: 3944.55 | F74: 0 | G74: 3944.55 | H74: -5369.45
A75: =IF(LEN(B75)=8,LEFT(B75,1),0) -> 0 | B75: C596211612 | C75: (-) ANTECIPAÇÃO DE I | D75: 0 | E75: 9314 | F75: 0 | G75: 9314 | H75: 9314
A76: =IF(LEN(B76)=8,LEFT(B76,1),0) -> 2 | B76: 21131102 | C76: (-) ANTECIPACAO IRPJ | D76: 0 | E76: 9314 | F76: 0 | G76: 9314 | H76: 9314
A77: =IF(LEN(B77)=8,LEFT(B77,1),0) -> 0 | B77: C59621162 | C77: CONTRIBUIÇÃO SOCIAL | D77: -4073.04 | E77: 4924.41 | F77: 0 | G77: 4924.41 | H77: 851.37
A78: =IF(LEN(B78)=8,LEFT(B78,1),0) -> 0 | B78: C596211621 | C78: CONTRIBUIÇÃO SOCIAL | D78: -4073.04 | E78: 851.37 | F78: 0 | G78: 851.37 | H78: -3221.67
A79: =IF(LEN(B79)=8,LEFT(B79,1),0) -> 2 | B79: 21131201 | C79: PROVISÃO PARA CSLL | D79: -4073.04 | E79: 851.37 | F79: 0 | G79: 851.37 | H79: -3221.67
A80: =IF(LEN(B80)=8,LEFT(B80,1),0) -> 0 | B80: C596211622 | C80: (-) ANTECIPAÇÃO DE C | D80: 0 | E80: 4073.04 | F80: 0 | G80: 4073.04 | H80: 4073.04
A81: =IF(LEN(B81)=8,LEFT(B81,1),0) -> 2 | B81: 21131202 | C81: (-) ANTECIPAÇÃO CSLL | D81: 0 | E81: 4073.04 | F81: 0 | G81: 4073.04 | H81: 4073.04
A82: =IF(LEN(B82)=8,LEFT(B82,1),0) -> 0 | B82: C59624 | C82: PATRIMÔNIO LÍQUIDO O | D82: -2613216.3 | E82: 0 | F82: 0 | G82: 0 | H82: -2613216.3
A83: =IF(LEN(B83)=8,LEFT(B83,1),0) -> 0 | B83: C596241 | C83: PATRIMÔNIO LÍQUIDO | D83: -2613216.3 | E83: 0 | F83: 0 | G83: 0 | H83: -2613216.3
A84: =IF(LEN(B84)=8,LEFT(B84,1),0) -> C | B84: C5962411 | C84: CAPITAL SOCIAL | D84: -1707264 | E84: 0 | F84: 0 | G84: 0 | H84: -1707264
A85: =IF(LEN(B85)=8,LEFT(B85,1),0) -> 0 | B85: C59624111 | C85: CAPITAL NACIONAL | D85: -1707264 | E85: 0 | F85: 0 | G85: 0 | H85: -1707264
A86: =IF(LEN(B86)=8,LEFT(B86,1),0) -> 0 | B86: C596241111 | C86: AÇÕES ORDINÁRIAS | D86: -1707264 | E86: 0 | F86: 0 | G86: 0 | H86: -1707264
A87: =IF(LEN(B87)=8,LEFT(B87,1),0) -> 2 | B87: 24111001 | C87: AÇÕES ORDINÁRIAS | D87: -1707264 | E87: 0 | F87: 0 | G87: 0 | H87: -1707264
A88: =IF(LEN(B88)=8,LEFT(B88,1),0) -> C | B88: C5962418 | C88: LUCROS OU PREJUÍZOS | D88: -905952.29 | E88: 0 | F88: 0 | G88: 0 | H88: -905952.29
A89: =IF(LEN(B89)=8,LEFT(B89,1),0) -> 0 | B89: C59624184 | C89: RESULTADO DO EXERCÍC | D89: -905952.29 | E89: 0 | F89: 0 | G89: 0 | H89: -905952.29
A90: =IF(LEN(B90)=8,LEFT(B90,1),0) -> 2 | B90: 24180004 | C90: RESULTADO EXERCÍCIO | D90: -905952.29 | E90: 0 | F90: 0 | G90: 0 | H90: -905952.29
A91: =IF(LEN(B91)=8,LEFT(B91,1),0) -> 0 | B91: C5963 | C91: RESULTADO | D91: 3183.33 | E91: 73323.93 | F91: 30247.37 | G91: 43076.56 | H91: 46259.89
A92: =IF(LEN(B92)=8,LEFT(B92,1),0) -> 0 | B92: C59631 | C92: OPERAÇÕES DE SEGUROS | D92: -2418.04 | E92: 34701.84 | F92: 11656.58 | G92: 23045.26 | H92: 20627.22
A93: =IF(LEN(B93)=8,LEFT(B93,1),0) -> 0 | B93: C596315 | C93: OUTRAS RECEITAS E DE | D93: -2418.04 | E93: 34701.84 | F93: 11656.58 | G93: 23045.26 | H93: 20627.22
A94: =IF(LEN(B94)=8,LEFT(B94,1),0) -> C | B94: C5963151 | C94: OUTRAS RECEITAS OPER | D94: -7990.17 | E94: 0 | F94: 3906.58 | G94: -3906.58 | H94: -11896.75
A95: =IF(LEN(B95)=8,LEFT(B95,1),0) -> 0 | B95: C59631518 | C95: OUTRAS RECEITAS COM | D95: -7990.17 | E95: 0 | F95: 3906.58 | G95: -3906.58 | H95: -11896.75
A96: =IF(LEN(B96)=8,LEFT(B96,1),0) -> 0 | B96: C596315189 | C96: OUTRAS RECEITAS | D96: -7990.17 | E96: 0 | F96: 3906.58 | G96: -3906.58 | H96: -11896.75
A97: =IF(LEN(B97)=8,LEFT(B97,1),0) -> 0 | B97: C5963151898 | C97: OUTRAS | D97: -7990.17 | E97: 0 | F97: 3906.58 | G97: -3906.58 | H97: -11896.75
A98: =IF(LEN(B98)=8,LEFT(B98,1),0) -> 3 | B98: 35199998 | C98: RECEITAS PREST SERV | D98: -7990.17 | E98: 0 | F98: 3906.58 | G98: -3906.58 | H98: -11896.75
A99: =IF(LEN(B99)=8,LEFT(B99,1),0) -> C | B99: C5963152 | C99: OUTRAS DESPESAS OPER | D99: 5572.13 | E99: 34701.84 | F99: 7750 | G99: 26951.84 | H99: 32523.97
A100: =IF(LEN(B100)=8,LEFT(B100,1),0) -> 0 | B100: C59631522 | C100: DESPESAS COM COBRANÇ | D100: 0 | E100: 7750 | F100: 7750 | G100: 0 | H100: 0
...

Sheet Bal 012026
B1: Table
C2: Exercício/período | D2: 001.2026 | E2: 001.2026 | F2: 001.2026 | G2: 001.2026 | H2: 001.2026
A3: =LEFT(B3,1) -> C | B3: Conta do Razão | D3: Saldo Anterior | E3: Débitos | F3: Créditos | G3: Movimento | H3: Saldo Acumulado
A4: =LEFT(B4,1) -> C | B4: C596 | C4: PLANO DE CONTAS SUSE | D4: -758085.45 | E4: 1327124.8 | F4: 1192194 | G4: 134930.72 | H4: -623154.73
A5: =LEFT(B5,1) -> C | B5: C5961 | C5: ATIVO | D5: 1960085.4 | E5: 769200 | F5: 632647.65 | G5: 136552.35 | H5: 2096637.8
A6: =LEFT(B6,1) -> C | B6: C59611 | C6: CIRCULANTE | D6: 1582307.6 | E6: 768671.32 | F6: 621007.86 | G6: 147663.46 | H6: 1729971.1
A7: =LEFT(B7,1) -> C | B7: C596111 | C7: DISPONÍVEL | D7: 8107.55 | E7: 671256.24 | F7: 620998.81 | G7: 50257.43 | H7: 58364.98
A8: =LEFT(B8,1) -> C | B8: C5961113 | C8: BANCOS CONTA DEPÓSIT | D8: 8107.55 | E8: 671256.24 | F8: 620998.81 | G8: 50257.43 | H8: 58364.98
A9: =LEFT(B9,1) -> C | B9: C59611131 | C9: BANCOS CONTA DEPÓSIT | D9: 8107.55 | E9: 671256.24 | F9: 620998.81 | G9: 50257.43 | H9: 58364.98
A10: =LEFT(B10,1) -> 1 | B10: 11131050 | C10: BCO SANTANDER | D10: 15479.85 | E10: 109949.19 | F10: 101220.56 | G10: 8728.63 | H10: 24208.48
A11: =LEFT(B11,1) -> 1 | B11: 11131090 | C11: BANCO SANTANDER | D11: 9954.11 | E11: 42818.33 | F11: 195.7 | G11: 42622.63 | H11: 52576.74
A12: =LEFT(B12,1) -> 1 | B12: 11132050 | C12: BCO SANTANDER | D12: -17317.36 | E12: 311733.68 | F12: 312837.56 | G12: -1103.88 | H12: -18421.24
A13: =LEFT(B13,1) -> 1 | B13: 11132090 | C13: BANCO SANTANDER | D13: -9.05 | E13: 84489.14 | F13: 84480.09 | G13: 9.05 | H13: 0
A14: =LEFT(B14,1) -> 1 | B14: 11133050 | C14: BCO SANTANDER SAIDA | D14: 0 | E14: 122257.12 | F14: 122256.12 | G14: 1 | H14: 1
A15: =LEFT(B15,1) -> 1 | B15: 11133090 | C15: BANCO SANTANDER | D15: 0 | E15: 8.78 | F15: 8.78 | G15: 0 | H15: 0
A16: =LEFT(B16,1) -> C | B16: C596112 | C16: APLICAÇÕES | D16: 528893.79 | E16: 86200.26 | F16: 0 | G16: 86200.26 | H16: 615094.05
A17: =LEFT(B17,1) -> C | B17: C5961126 | C17: QUOTAS DE FUNDOS DE | D17: 528893.79 | E17: 86200.26 | F17: 0 | G17: 86200.26 | H17: 615094.05
A18: =LEFT(B18,1) -> C | B18: C59611261 | C18: VINCULADAS À COBERTU | D18: 528893.79 | E18: 86200.26 | F18: 0 | G18: 86200.26 | H18: 615094.05
A19: =LEFT(B19,1) -> C | B19: C596112612 | C19: QUOTAS DE OUTROS FUN | D19: 528893.79 | E19: 86200.26 | F19: 0 | G19: 86200.26 | H19: 615094.05
A20: =LEFT(B20,1) -> C | B20: C5961126121 | C20: VALOR ORIGINAL | D20: 528893.79 | E20: 86200.26 | F20: 0 | G20: 86200.26 | H20: 615094.05
A21: =LEFT(B21,1) -> 1 | B21: 11240001 | C21: FD ÑEX CUV VC CP DPV | D21: 528893.79 | E21: 86200.26 | F21: 0 | G21: 86200.26 | H21: 615094.05
A22: =LEFT(B22,1) -> C | B22: C596113 | C22: CRÉDITOS DAS OPERAÇÕ | D22: 0 | E22: 9.05 | F22: 9.05 | G22: 0 | H22: 0
A23: =LEFT(B23,1) -> C | B23: C5961138 | C23: OUTROS CRÉDITOS OPER | D23: 0 | E23: 9.05 | F23: 9.05 | G23: 0 | H23: 0
A24: =LEFT(B24,1) -> C | B24: C59611388 | C24: OUTROS CRÉDITOS | D24: 0 | E24: 9.05 | F24: 9.05 | G24: 0 | H24: 0
A25: =LEFT(B25,1) -> 1 | B25: 11391098 | C25: CRED OPR CONCILIAÇÃO | D25: 0 | E25: 9.05 | F25: 9.05 | G25: 0 | H25: 0
A26: =LEFT(B26,1) -> C | B26: C596114 | C26: TÍTULOS E CRÉDITOS A | D26: 1045306.3 | E26: 11205.77 | F26: 0 | G26: 11205.77 | H26: 1056512.1
A27: =LEFT(B27,1) -> C | B27: C5961141 | C27: CRÉDITOS A RECEBER | D27: 158968.63 | E27: 0 | F27: 0 | G27: 0 | H27: 158968.63
A28: =LEFT(B28,1) -> C | B28: C59611418 | C28: OUTROS CRÉDITOS A RE | D28: 158968.63 | E28: 0 | F28: 0 | G28: 0 | H28: 158968.63
A29: =LEFT(B29,1) -> 1 | B29: 11610099 | C29: OUTROS CRÉD.RECEBER | D29: 158968.63 | E29: 0 | F29: 0 | G29: 0 | H29: 158968.63
A30: =LEFT(B30,1) -> C | B30: C5961144 | C30: CRÉDITOS TRIBUTÁRIOS | D30: 886337.67 | E30: 11205.77 | F30: 0 | G30: 11205.77 | H30: 897543.44
A31: =LEFT(B31,1) -> C | B31: C59611441 | C31: CRÉDITOS DE IMPOSTO | D31: 131562.4 | E31: 3399.58 | F31: 0 | G31: 3399.58 | H31: 134961.98
A32: =LEFT(B32,1) -> C | B32: C596114411 | C32: IMPOSTO DE RENDA A C | D32: 101235.55 | E32: 3399.58 | F32: 0 | G32: 3399.58 | H32: 104635.13
A33: =LEFT(B33,1) -> 1 | B33: 11641001 | C33: IRPJ A COMPENSAR CP | D33: 101235.55 | E33: 3399.58 | F33: 0 | G33: 3399.58 | H33: 104635.13
A34: =LEFT(B34,1) -> C | B34: C596114412 | C34: ANTECIPAÇÃO DE IMPOS | D34: 30326.85 | E34: 0 | F34: 0 | G34: 0 | H34: 30326.85
A35: =LEFT(B35,1) -> 1 | B35: 11641002 | C35: ANTECIPAÇÃO DE IRPJ | D35: 30326.85 | E35: 0 | F35: 0 | G35: 0 | H35: 30326.85
A36: =LEFT(B36,1) -> C | B36: C59611442 | C36: CRÉDITOS DE CONTRIBU | D36: 754775.27 | E36: 7806.19 | F36: 0 | G36: 7806.19 | H36: 762581.46
A37: =LEFT(B37,1) -> C | B37: C596114421 | C37: CONTRIBUIÇÃO SOCIAL | D37: 740918.81 | E37: 7806.19 | F37: 0 | G37: 7806.19 | H37: 748725
A38: =LEFT(B38,1) -> 1 | B38: 11642001 | C38: CSLL A COMPENSAR CP | D38: 740918.81 | E38: 7806.19 | F38: 0 | G38: 7806.19 | H38: 748725
A39: =LEFT(B39,1) -> C | B39: C596114422 | C39: ANTECIPAÇÃO DE CONTR | D39: 13856.46 | E39: 0 | F39: 0 | G39: 0 | H39: 13856.46
A40: =LEFT(B40,1) -> 1 | B40: 11642002 | C40: ANTECIPAÇÃO DE CSLL | D40: 13856.46 | E40: 0 | F40: 0 | G40: 0 | H40: 13856.46
A41: =LEFT(B41,1) -> C | B41: C59612 | C41: ATIVO NÃO CIRCULANTE | D41: 377777.79 | E41: 528.68 | F41: 11639.79 | G41: -11111.11 | H41: 366666.68
A42: =LEFT(B42,1) -> C | B42: C596121 | C42: REALIZÁVEL A LONGO P | D42: 377777.79 | E42: 528.68 | F42: 11639.79 | G42: -11111.11 | H42: 366666.68
A43: =LEFT(B43,1) -> C | B43: C5961213 | C43: TÍTULOS E CRÉDITOS A | D43: 377777.79 | E43: 528.68 | F43: 11639.79 | G43: -11111.11 | H43: 366666.68
A44: =LEFT(B44,1) -> C | B44: C59612131 | C44: CRÉDITOS A RECEBER | D44: 377777.79 | E44: 528.68 | F44: 11639.79 | G44: -11111.11 | H44: 366666.68
A45: =LEFT(B45,1) -> C | B45: C596121311 | C45: CRÉDITOS A RECEBER | D45: 377777.79 | E45: 528.68 | F45: 11639.79 | G45: -11111.11 | H45: 366666.68
A46: =LEFT(B46,1) -> 1 | B46: 12610001 | C46: CRÉDITOS RECEBER-LP | D46: 377777.79 | E46: 528.68 | F46: 11639.79 | G46: -11111.11 | H46: 366666.68
A47: =LEFT(B47,1) -> C | B47: C596123 | C47: IMOBILIZADO | D47: 0 | E47: 0 | F47: 0 | G47: 0 | H47: 0
A48: =LEFT(B48,1) -> C | B48: C5961232 | C48: EQUIPAMENTOS | D48: 0 | E48: 0 | F48: 0 | G48: 0 | H48: 0
A49: =LEFT(B49,1) -> C | B49: C59612321 | C49: INFORMÁTICA | D49: 16679.39 | E49: 0 | F49: 0 | G49: 0 | H49: 16679.39
A50: =LEFT(B50,1) -> C | B50: C596123211 | C50: HARDWARE | D50: 16679.39 | E50: 0 | F50: 0 | G50: 0 | H50: 16679.39
A51: =LEFT(B51,1) -> 1 | B51: 14221001 | C51: EQTOS DE INFORMATICA | D51: 16679.39 | E51: 0 | F51: 0 | G51: 0 | H51: 16679.39
A52: =LEFT(B52,1) -> C | B52: C59612322 | C52: TELECOMUNICAÇÕES | D52: 6147 | E52: 0 | F52: 0 | G52: 0 | H52: 6147
A53: =LEFT(B53,1) -> 1 | B53: 14222001 | C53: TELECOMUNICAÇÕES | D53: 6147 | E53: 0 | F53: 0 | G53: 0 | H53: 6147
A54: =LEFT(B54,1) -> C | B54: C59612329 | C54: DEPRECIAÇÃO ACUMULAD | D54: -22826.39 | E54: 0 | F54: 0 | G54: 0 | H54: -22826.39
A55: =LEFT(B55,1) -> C | B55: C596123291 | C55: DEPRECIAÇÃO ACUMULAD | D55: -22826.39 | E55: 0 | F55: 0 | G55: 0 | H55: -22826.39
A56: =LEFT(B56,1) -> 1 | B56: 14229001 | C56: DEP.ACUM EQTO INFORM | D56: -16679.39 | E56: 0 | F56: 0 | G56: 0 | H56: -16679.39
A57: =LEFT(B57,1) -> 1 | B57: 14229003 | C57: DEP.ACUM TELECOMUNIC | D57: -6147 | E57: 0 | F57: 0 | G57: 0 | H57: -6147
A58: =LEFT(B58,1) -> C | B58: C5962 | C58: PASSIVO | D58: -2718170.9 | E58: 287675.85 | F58: 292480.81 | G58: -4804.96 | H58: -2722975.8
A59: =LEFT(B59,1) -> C | B59: C59621 | C59: CIRCULANTE | D59: -104954.59 | E59: 287675.85 | F59: 292480.81 | G59: -4804.96 | H59: -109759.55
A60: =LEFT(B60,1) -> C | B60: C596211 | C60: CONTAS A PAGAR | D60: -104954.59 | E60: 287675.85 | F60: 292480.81 | G60: -4804.96 | H60: -109759.55
A61: =LEFT(B61,1) -> C | B61: C5962111 | C61: OBRIGAÇÕES A PAGAR | D61: -85928.53 | E61: 21128.06 | F61: 26700.19 | G61: -5572.13 | H61: -91500.66
A62: =LEFT(B62,1) -> C | B62: C59621111 | C62: FORNECEDORES | D62: -83309.5 | E62: 21128.06 | F62: 21128.06 | G62: 0 | H62: -83309.5
A63: =LEFT(B63,1) -> 2 | B63: 21111001 | C63: FORN BENS SERVIÇOS | D63: -83309.5 | E63: 21128.06 | F63: 21128.06 | G63: 0 | H63: -83309.5
A64: =LEFT(B64,1) -> C | B64: C59621119 | C64: OUTRAS OBRIGAÇÕES A | D64: -2619.03 | E64: 0 | F64: 5572.13 | G64: -5572.13 | H64: -8191.16
A65: =LEFT(B65,1) -> C | B65: C596211198 | C65: OUTRAS OBRIGAÇÕES | D65: -2619.03 | E65: 0 | F65: 5572.13 | G65: -5572.13 | H65: -8191.16
A66: =LEFT(B66,1) -> 2 | B66: 21111099 | C66: OUTRAS OBRIG.PAGAR | D66: -2619.03 | E66: 0 | F66: 5572.13 | G66: -5572.13 | H66: -8191.16
A67: =LEFT(B67,1) -> C | B67: C5962112 | C67: IMPOSTOS E ENCARGOS | D67: -9662.33 | E67: 14268.59 | F67: 9478.11 | G67: 4790.48 | H67: -4871.85
A68: =LEFT(B68,1) -> C | B68: C59621122 | C68: IMPOSTO DE RENDA RET | D68: -1470.52 | E68: 1470.52 | F68: 0 | G68: 1470.52 | H68: 0
A69: =LEFT(B69,1) -> 2 | B69: 21131104 | C69: IRF TERCEIROS RECOL | D69: -1470.52 | E69: 1470.52 | F69: 0 | G69: 1470.52 | H69: 0
A70: =LEFT(B70,1) -> C | B70: C59621128 | C70: OUTROS IMPOSTOS E EN | D70: -8191.81 | E70: 12798.07 | F70: 9478.11 | G70: 3319.96 | H70: -4871.85
A71: =LEFT(B71,1) -> 2 | B71: 21131601 | C71: COFINS A RECOLHER | D71: -3013.61 | E71: 6843.37 | F71: 7859.46 | G71: -1016.09 | H71: -4029.7
A72: =LEFT(B72,1) -> 2 | B72: 21131602 | C72: PIS/PASEP A RECOLHER | D72: -619.61 | E72: 1396.11 | F72: 1618.65 | G72: -222.54 | H72: -842.15
A73: =LEFT(B73,1) -> 2 | B73: 21131701 | C73: PIS/COFINS/CSLL TERC | D73: -4558.59 | E73: 4558.59 | F73: 0 | G73: 4558.59 | H73: 0
A74: =LEFT(B74,1) -> C | B74: C5962116 | C74: IMPOSTOS E CONTRIBUI | D74: -9363.73 | E74: 252279.2 | F74: 256302.51 | G74: -4023.31 | H74: -13387.04
A75: =LEFT(B75,1) -> C | B75: C59621161 | C75: IMPOSTO DE RENDA | D75: -5517.91 | E75: 177143.31 | F75: 180939.4 | G75: -3796.09 | H75: -9314
A76: =LEFT(B76,1) -> C | B76: C596211611 | C76: IMPOSTO DE RENDA | D76: -169251.71 | E76: 169251.71 | F76: 9314 | G76: 159937.71 | H76: -9314
A77: =LEFT(B77,1) -> 2 | B77: 21131101 | C77: PROVISÃO PARA IRPJ | D77: -169251.71 | E77: 169251.71 | F77: 9314 | G77: 159937.71 | H77: -9314
A78: =LEFT(B78,1) -> C | B78: C596211612 | C78: (-) ANTECIPAÇÃO DE I | D78: 163733.8 | E78: 7891.6 | F78: 171625.4 | G78: -163733.8 | H78: 0
A79: =LEFT(B79,1) -> 2 | B79: 21131102 | C79: (-) ANTECIPACAO IRPJ | D79: 163733.8 | E79: 7891.6 | F79: 171625.4 | G79: -163733.8 | H79: 0
A80: =LEFT(B80,1) -> C | B80: C59621162 | C80: CONTRIBUIÇÃO SOCIAL | D80: -3845.82 | E80: 75135.89 | F80: 75363.11 | G80: -227.22 | H80: -4073.04
A81: =LEFT(B81,1) -> C | B81: C596211621 | C81: CONTRIBUIÇÃO SOCIAL | D81: -70709.99 | E81: 70709.99 | F81: 4073.04 | G81: 66636.95 | H81: -4073.04
A82: =LEFT(B82,1) -> 2 | B82: 21131201 | C82: PROVISÃO PARA CSLL | D82: -70709.99 | E82: 70709.99 | F82: 4073.04 | G82: 66636.95 | H82: -4073.04
A83: =LEFT(B83,1) -> C | B83: C596211622 | C83: (-) ANTECIPAÇÃO DE C | D83: 66864.17 | E83: 4425.9 | F83: 71290.07 | G83: -66864.17 | H83: 0
A84: =LEFT(B84,1) -> 2 | B84: 21131202 | C84: (-) ANTECIPAÇÃO CSLL | D84: 66864.17 | E84: 4425.9 | F84: 71290.07 | G84: -66864.17 | H84: 0
A85: =LEFT(B85,1) -> C | B85: C59624 | C85: PATRIMÔNIO LÍQUIDO O | D85: -2613216.3 | E85: 0 | F85: 0 | G85: 0 | H85: -2613216.3
A86: =LEFT(B86,1) -> C | B86: C596241 | C86: PATRIMÔNIO LÍQUIDO | D86: -2613216.3 | E86: 0 | F86: 0 | G86: 0 | H86: -2613216.3
A87: =LEFT(B87,1) -> C | B87: C5962411 | C87: CAPITAL SOCIAL | D87: -1707264 | E87: 0 | F87: 0 | G87: 0 | H87: -1707264
A88: =LEFT(B88,1) -> C | B88: C59624111 | C88: CAPITAL NACIONAL | D88: -1707264 | E88: 0 | F88: 0 | G88: 0 | H88: -1707264
A89: =LEFT(B89,1) -> C | B89: C596241111 | C89: AÇÕES ORDINÁRIAS | D89: -1707264 | E89: 0 | F89: 0 | G89: 0 | H89: -1707264
A90: =LEFT(B90,1) -> 2 | B90: 24111001 | C90: AÇÕES ORDINÁRIAS | D90: -1707264 | E90: 0 | F90: 0 | G90: 0 | H90: -1707264
A91: =LEFT(B91,1) -> C | B91: C5962418 | C91: LUCROS OU PREJUÍZOS | D91: -905952.29 | E91: 0 | F91: 0 | G91: 0 | H91: -905952.29
A92: =LEFT(B92,1) -> C | B92: C59624184 | C92: RESULTADO DO EXERCÍC | D92: -905952.29 | E92: 0 | F92: 0 | G92: 0 | H92: -905952.29
A93: =LEFT(B93,1) -> 2 | B93: 24180004 | C93: RESULTADO EXERCÍCIO | D93: -905952.29 | E93: 0 | F93: 0 | G93: 0 | H93: -905952.29
A94: =LEFT(B94,1) -> C | B94: C5963 | C94: RESULTADO | D94: 0 | E94: 270248.9 | F94: 267065.57 | G94: 3183.33 | H94: 3183.33
A95: =LEFT(B95,1) -> C | B95: C59631 | C95: OPERAÇÕES DE SEGUROS | D95: 0 | E95: 5572.13 | F95: 7990.17 | G95: -2418.04 | H95: -2418.04
A96: =LEFT(B96,1) -> C | B96: C596315 | C96: OUTRAS RECEITAS E DE | D96: 0 | E96: 5572.13 | F96: 7990.17 | G96: -2418.04 | H96: -2418.04
A97: =LEFT(B97,1) -> C | B97: C5963151 | C97: OUTRAS RECEITAS OPER | D97: 0 | E97: 0 | F97: 7990.17 | G97: -7990.17 | H97: -7990.17
A98: =LEFT(B98,1) -> C | B98: C59631518 | C98: OUTRAS RECEITAS COM | D98: 0 | E98: 0 | F98: 7990.17 | G98: -7990.17 | H98: -7990.17
A99: =LEFT(B99,1) -> C | B99: C596315189 | C99: OUTRAS RECEITAS | D99: 0 | E99: 0 | F99: 7990.17 | G99: -7990.17 | H99: -7990.17
A100: =LEFT(B100,1) -> C | B100: C5963151898 | C100: OUTRAS | D100: 0 | E100: 0 | F100: 7990.17 | G100: -7990.17 | H100: -7990.17
...

Sheet Bal 12.2026
H28: =G27+G28 -> 0
H30: =G29+G30 -> 0

Sheet Bal 11.2026
H28: =G27+G28 -> 0
H30: =G29+G30 -> 0

Sheet Bal 10.2026
H28: =G27+G28 -> 0
H30: =G29+G30 -> 0

Sheet Bal 09.2026

Sheet Bal 08.2026

Sheet Bal 07.2026
